Workbook

Sheet Dashboard
A1: Project Name | B1: 219 Driggs Street
A2: Address | B2: 219 Driggs Street
A3: Project Size | B3: 10000
B7: Project Budget

Sheet Team
A1: Contact | B1: Company | C1: Email | D1: Open Tasks | E1: In Progress Tasks | F1: Completed Tasks | G1: Total Tasks
A2: Middleton Environmental | Thomas R. Tompkins | B2: =if(len(A2)>0, VLOOKUP(A2,Lookup!$A$2:$F1000,3,FALSE),"") -> Middleton Environmental | C2: =if(len(A2)>0, VLOOKUP(A2,Lookup!$A$2:$F1000,6,FALSE),"") -> info@midenv.com | D2: =countifs(TasksToDo!$C$2:$C1000,$A2,TasksToDo!$G$2:$G1000,"Pending") -> 0 | E2: =countifs(TasksToDo!$C$2:$C1000,$A2,TasksToDo!$G$2:$G1000,"In Progress") -> 0 | F2: =countifs(TasksToDo!$C$2:$C1000,$A2,TasksToDo!$G$2:$G1000,"Completed") -> 0 | G2: =SUM(D2:F2) -> 0
A3: International Office of Architects | Murat Mutlu | B3: =if(len(A3)>0, VLOOKUP(A3,Lookup!$A$2:$F1000,3,FALSE),"") -> International Office of Architects | C3: =if(len(A3)>0, VLOOKUP(A3,Lookup!$A$2:$F1000,6,FALSE),"") -> murat@in-oa.com | D3: =countifs(TasksToDo!$C$2:$C1000,$A3,TasksToDo!$G$2:$G1000,"Pending") -> 0 | E3: =countifs(TasksToDo!$C$2:$C1000,$A3,TasksToDo!$G$2:$G1000,"In Progress") -> 0 | F3: =countifs(TasksToDo!$C$2:$C1000,$A3,TasksToDo!$G$2:$G1000,"Completed") -> 0 | G3: =SUM(D3:F3) -> 0
A4: Stroh Engineering Services | Jeff Roberts | B4: =if(len(A4)>0, VLOOKUP(A4,Lookup!$A$2:$F1000,3,FALSE),"") -> Stroh Engineering Services | C4: =if(len(A4)>0, VLOOKUP(A4,Lookup!$A$2:$F1000,6,FALSE),"") -> jeff@strohengineering.com | D4: =countifs(TasksToDo!$C$2:$C1000,$A4,TasksToDo!$G$2:$G1000,"Pending") -> 0 | E4: =countifs(TasksToDo!$C$2:$C1000,$A4,TasksToDo!$G$2:$G1000,"In Progress") -> 0 | F4: =countifs(TasksToDo!$C$2:$C1000,$A4,TasksToDo!$G$2:$G1000,"Completed") -> 0 | G4: =SUM(D4:F4) -> 0
A5: Boyd Consulting | Andrea Boyd | B5: =if(len(A5)>0, VLOOKUP(A5,Lookup!$A$2:$F1000,3,FALSE),"") -> Boyd Consulting | C5: =if(len(A5)>0, VLOOKUP(A5,Lookup!$A$2:$F1000,6,FALSE),"") -> andrea@boydconsult.com | D5: =countifs(TasksToDo!$C$2:$C1000,$A5,TasksToDo!$G$2:$G1000,"Pending") -> 0 | E5: =countifs(TasksToDo!$C$2:$C1000,$A5,TasksToDo!$G$2:$G1000,"In Progress") -> 0 | F5: =countifs(TasksToDo!$C$2:$C1000,$A5,TasksToDo!$G$2:$G1000,"Completed") -> 0 | G5: =SUM(D5:F5) -> 0
A6: 5 Borough Mapping NY | Raj Kumar | B6: =if(len(A6)>0, VLOOKUP(A6,Lookup!$A$2:$F1000,3,FALSE),"") -> 5 Borough Mapping NY | C6: =if(len(A6)>0, VLOOKUP(A6,Lookup!$A$2:$F1000,6,FALSE),"") -> 5boromapping@gmail.com | D6: =countifs(TasksToDo!$C$2:$C1000,$A6,TasksToDo!$G$2:$G1000,"Pending") -> 0 | E6: =countifs(TasksToDo!$C$2:$C1000,$A6,TasksToDo!$G$2:$G1000,"In Progress") -> 0 | F6: =countifs(TasksToDo!$C$2:$C1000,$A6,TasksToDo!$G$2:$G1000,"Completed") -> 0 | G6: =SUM(D6:F6) -> 0
A7: Preferred Bank | Sylvia Tseng | B7: =if(len(A7)>0, VLOOKUP(A7,Lookup!$A$2:$F1000,3,FALSE),"") -> Preferred Bank | C7: =if(len(A7)>0, VLOOKUP(A7,Lookup!$A$2:$F1000,6,FALSE),"") -> Sylvia.Tseng@PreferredBank.com | D7: =countifs(TasksToDo!$C$2:$C1000,$A7,TasksToDo!$G$2:$G1000,"Pending") -> 0 | E7: =countifs(TasksToDo!$C$2:$C1000,$A7,TasksToDo!$G$2:$G1000,"In Progress") -> 0 | F7: =countifs(TasksToDo!$C$2:$C1000,$A7,TasksToDo!$G$2:$G1000,"Completed") -> 0 | G7: =SUM(D7:F7) -> 0
A8: DGM CPA | George Mataev | B8: =if(len(A8)>0, VLOOKUP(A8,Lookup!$A$2:$F1000,3,FALSE),"") -> DGM CPA | C8: =if(len(A8)>0, VLOOKUP(A8,Lookup!$A$2:$F1000,6,FALSE),"") -> george@dgmcpany.com | D8: =countifs(TasksToDo!$C$2:$C1000,$A8,TasksToDo!$G$2:$G1000,"Pending") -> 0 | E8: =countifs(TasksToDo!$C$2:$C1000,$A8,TasksToDo!$G$2:$G1000,"In Progress") -> 0 | F8: =countifs(TasksToDo!$C$2:$C1000,$A8,TasksToDo!$G$2:$G1000,"Completed") -> 0 | G8: =SUM(D8:F8) -> 0
A9: Marcus Attorneys PLLC | Guillermo Santiago | B9: =if(len(A9)>0, VLOOKUP(A9,Lookup!$A$2:$F1000,3,FALSE),"") -> Marcus Attorneys PLLC | C9: =if(len(A9)>0, VLOOKUP(A9,Lookup!$A$2:$F1000,6,FALSE),"") -> santiago@marcusattorneys.com | D9: =countifs(TasksToDo!$C$2:$C1000,$A9,TasksToDo!$G$2:$G1000,"Pending") -> 0 | E9: =countifs(TasksToDo!$C$2:$C1000,$A9,TasksToDo!$G$2:$G1000,"In Progress") -> 0 | F9: =countifs(TasksToDo!$C$2:$C1000,$A9,TasksToDo!$G$2:$G1000,"Completed") -> 0 | G9: =SUM(D9:F9) -> 0
A10: MCAI Construction Services | Noel G Muir | B10: =if(len(A10)>0, VLOOKUP(A10,Lookup!$A$2:$F1000,3,FALSE),"") -> MCAI Construction Services | C10: =if(len(A10)>0, VLOOKUP(A10,Lookup!$A$2:$F1000,6,FALSE),"") -> mcai079@aol.com | D10: =countifs(TasksToDo!$C$2:$C1000,$A10,TasksToDo!$G$2:$G1000,"Pending") -> 0 | E10: =countifs(TasksToDo!$C$2:$C1000,$A10,TasksToDo!$G$2:$G1000,"In Progress") -> 0 | F10: =countifs(TasksToDo!$C$2:$C1000,$A10,TasksToDo!$G$2:$G1000,"Completed") -> 0 | G10: =SUM(D10:F10) -> 0
A11: Exterior Design Renterings | Andrew Melnikov | B11: =if(len(A11)>0, VLOOKUP(A11,Lookup!$A$2:$F1000,3,FALSE),"") -> Exterior Design Renterings | C11: =if(len(A11)>0, VLOOKUP(A11,Lookup!$A$2:$F1000,6,FALSE),"") | D11: =countifs(TasksToDo!$C$2:$C1000,$A11,TasksToDo!$G$2:$G1000,"Pending") -> 0 | E11: =countifs(TasksToDo!$C$2:$C1000,$A11,TasksToDo!$G$2:$G1000,"In Progress") -> 0 | F11: =countifs(TasksToDo!$C$2:$C1000,$A11,TasksToDo!$G$2:$G1000,"Completed") -> 0 | G11: =SUM(D11:F11) -> 0
A12: Yaker Engineering | Alex Yaker | B12: =if(len(A12)>0, VLOOKUP(A12,Lookup!$A$2:$F1000,3,FALSE),"") -> Yaker Engineering | C12: =if(len(A12)>0, VLOOKUP(A12,Lookup!$A$2:$F1000,6,FALSE),"") -> ayaker@yakereng.com | D12: =countifs(TasksToDo!$C$2:$C1000,$A12,TasksToDo!$G$2:$G1000,"Pending") -> 0 | E12: =countifs(TasksToDo!$C$2:$C1000,$A12,TasksToDo!$G$2:$G1000,"In Progress") -> 0 | F12: =countifs(TasksToDo!$C$2:$C1000,$A12,TasksToDo!$G$2:$G1000,"Completed") -> 0 | G12: =SUM(D12:F12) -> 0
A13: WJY MEP Consulting Services, Inc | Wei Wang | B13: =if(len(A13)>0, VLOOKUP(A13,Lookup!$A$2:$F1000,3,FALSE),"") -> WJY MEP Consulting Services, Inc | C13: =if(len(A13)>0, VLOOKUP(A13,Lookup!$A$2:$F1000,6,FALSE),"") -> weiwilliamworld@yahoo.com | D13: =countifs(TasksToDo!$C$2:$C1000,$A13,TasksToDo!$G$2:$G1000,"Pending") -> 0 | E13: =countifs(TasksToDo!$C$2:$C1000,$A13,TasksToDo!$G$2:$G1000,"In Progress") -> 0 | F13: =countifs(TasksToDo!$C$2:$C1000,$A13,TasksToDo!$G$2:$G1000,"Completed") -> 0 | G13: =SUM(D13:F13) -> 0
B14: =if(len(A14)>0, VLOOKUP(A14,Lookup!$A$2:$F1000,3,FALSE),"") | C14: =if(len(A14)>0, VLOOKUP(A14,Lookup!$A$2:$F1000,6,FALSE),"")
C15: =if(len(A15)>0, VLOOKUP(A15,Lookup!$A$2:$F1000,6,FALSE),"")
C16: =if(len(A16)>0, VLOOKUP(A16,Lookup!$A$2:$F1000,6,FALSE),"")
C17: =if(len(A17)>0, VLOOKUP(A17,Lookup!$A$2:$F1000,6,FALSE),"")
C18: =if(len(A18)>0, VLOOKUP(A18,Lookup!$A$2:$F1000,6,FALSE),"")
C19: =if(len(A19)>0, VLOOKUP(A19,Lookup!$A$2:$F1000,6,FALSE),"")
C20: =if(len(A20)>0, VLOOKUP(A20,Lookup!$A$2:$F1000,6,FALSE),"")
C21: =if(len(A21)>0, VLOOKUP(A21,Lookup!$A$2:$F1000,6,FALSE),"")
C22: =if(len(A22)>0, VLOOKUP(A22,Lookup!$A$2:$F1000,6,FALSE),"")
C23: =if(len(A23)>0, VLOOKUP(A23,Lookup!$A$2:$F1000,6,FALSE),"")
C24: =if(len(A24)>0, VLOOKUP(A24,Lookup!$A$2:$F1000,6,FALSE),"")
C25: =if(len(A25)>0, VLOOKUP(A25,Lookup!$A$2:$F1000,6,FALSE),"")
C26: =if(len(A26)>0, VLOOKUP(A26,Lookup!$A$2:$F1000,6,FALSE),"")
C27: =if(len(A27)>0, VLOOKUP(A27,Lookup!$A$2:$F1000,6,FALSE),"")
C28: =if(len(A28)>0, VLOOKUP(A28,Lookup!$A$2:$F1000,6,FALSE),"")
C29: =if(len(A29)>0, VLOOKUP(A29,Lookup!$A$2:$F1000,6,FALSE),"")
C30: =if(len(A30)>0, VLOOKUP(A30,Lookup!$A$2:$F1000,6,FALSE),"")
C31: =if(len(A31)>0, VLOOKUP(A31,Lookup!$A$2:$F1000,6,FALSE),"")
C32: =if(len(A32)>0, VLOOKUP(A32,Lookup!$A$2:$F1000,6,FALSE),"")
C33: =if(len(A33)>0, VLOOKUP(A33,Lookup!$A$2:$F1000,6,FALSE),"")
C34: =if(len(A34)>0, VLOOKUP(A34,Lookup!$A$2:$F1000,6,FALSE),"")
C35: =if(len(A35)>0, VLOOKUP(A35,Lookup!$A$2:$F1000,6,FALSE),"")
C36: =if(len(A36)>0, VLOOKUP(A36,Lookup!$A$2:$F1000,6,FALSE),"")
C37: =if(len(A37)>0, VLOOKUP(A37,Lookup!$A$2:$F1000,6,FALSE),"")
C38: =if(len(A38)>0, VLOOKUP(A38,Lookup!$A$2:$F1000,6,FALSE),"")
C39: =if(len(A39)>0, VLOOKUP(A39,Lookup!$A$2:$F1000,6,FALSE),"")
C40: =if(len(A40)>0, VLOOKUP(A40,Lookup!$A$2:$F1000,6,FALSE),"")
C41: =if(len(A41)>0, VLOOKUP(A41,Lookup!$A$2:$F1000,6,FALSE),"")
C42: =if(len(A42)>0, VLOOKUP(A42,Lookup!$A$2:$F1000,6,FALSE),"")
C43: =if(len(A43)>0, VLOOKUP(A43,Lookup!$A$2:$F1000,6,FALSE),"")
C44: =if(len(A44)>0, VLOOKUP(A44,Lookup!$A$2:$F1000,6,FALSE),"")
C45: =if(len(A45)>0, VLOOKUP(A45,Lookup!$A$2:$F1000,6,FALSE),"")
C46: =if(len(A46)>0, VLOOKUP(A46,Lookup!$A$2:$F1000,6,FALSE),"")
C47: =if(len(A47)>0, VLOOKUP(A47,Lookup!$A$2:$F1000,6,FALSE),"")
C48: =if(len(A48)>0, VLOOKUP(A48,Lookup!$A$2:$F1000,6,FALSE),"")
C49: =if(len(A49)>0, VLOOKUP(A49,Lookup!$A$2:$F1000,6,FALSE),"")
C50: =if(len(A50)>0, VLOOKUP(A50,Lookup!$A$2:$F1000,6,FALSE),"")
C51: =if(len(A51)>0, VLOOKUP(A51,Lookup!$A$2:$F1000,6,FALSE),"")
C52: =if(len(A52)>0, VLOOKUP(A52,Lookup!$A$2:$F1000,6,FALSE),"")
C53: =if(len(A53)>0, VLOOKUP(A53,Lookup!$A$2:$F1000,6,FALSE),"")
C54: =if(len(A54)>0, VLOOKUP(A54,Lookup!$A$2:$F1000,6,FALSE),"")
C55: =if(len(A55)>0, VLOOKUP(A55,Lookup!$A$2:$F1000,6,FALSE),"")
C56: =if(len(A56)>0, VLOOKUP(A56,Lookup!$A$2:$F1000,6,FALSE),"")
C57: =if(len(A57)>0, VLOOKUP(A57,Lookup!$A$2:$F1000,6,FALSE),"")
C58: =if(len(A58)>0, VLOOKUP(A58,Lookup!$A$2:$F1000,6,FALSE),"")
C59: =if(len(A59)>0, VLOOKUP(A59,Lookup!$A$2:$F1000,6,FALSE),"")
C60: =if(len(A60)>0, VLOOKUP(A60,Lookup!$A$2:$F1000,6,FALSE),"")
C61: =if(len(A61)>0, VLOOKUP(A61,Lookup!$A$2:$F1000,6,FALSE),"")
C62: =if(len(A62)>0, VLOOKUP(A62,Lookup!$A$2:$F1000,6,FALSE),"")
C63: =if(len(A63)>0, VLOOKUP(A63,Lookup!$A$2:$F1000,6,FALSE),"")
C64: =if(len(A64)>0, VLOOKUP(A64,Lookup!$A$2:$F1000,6,FALSE),"")
C65: =if(len(A65)>0, VLOOKUP(A65,Lookup!$A$2:$F1000,6,FALSE),"")
C66: =if(len(A66)>0, VLOOKUP(A66,Lookup!$A$2:$F1000,6,FALSE),"")
C67: =if(len(A67)>0, VLOOKUP(A67,Lookup!$A$2:$F1000,6,FALSE),"")
C68: =if(len(A68)>0, VLOOKUP(A68,Lookup!$A$2:$F1000,6,FALSE),"")
C69: =if(len(A69)>0, VLOOKUP(A69,Lookup!$A$2:$F1000,6,FALSE),"")
C70: =if(len(A70)>0, VLOOKUP(A70,Lookup!$A$2:$F1000,6,FALSE),"")
C71: =if(len(A71)>0, VLOOKUP(A71,Lookup!$A$2:$F1000,6,FALSE),"")
C72: =if(len(A72)>0, VLOOKUP(A72,Lookup!$A$2:$F1000,6,FALSE),"")
C73: =if(len(A73)>0, VLOOKUP(A73,Lookup!$A$2:$F1000,6,FALSE),"")
C74: =if(len(A74)>0, VLOOKUP(A74,Lookup!$A$2:$F1000,6,FALSE),"")
C75: =if(len(A75)>0, VLOOKUP(A75,Lookup!$A$2:$F1000,6,FALSE),"")
C76: =if(len(A76)>0, VLOOKUP(A76,Lookup!$A$2:$F1000,6,FALSE),"")
C77: =if(len(A77)>0, VLOOKUP(A77,Lookup!$A$2:$F1000,6,FALSE),"")
C78: =if(len(A78)>0, VLOOKUP(A78,Lookup!$A$2:$F1000,6,FALSE),"")
C79: =if(len(A79)>0, VLOOKUP(A79,Lookup!$A$2:$F1000,6,FALSE),"")
C80: =if(len(A80)>0, VLOOKUP(A80,Lookup!$A$2:$F1000,6,FALSE),"")
C81: =if(len(A81)>0, VLOOKUP(A81,Lookup!$A$2:$F1000,6,FALSE),"")
C82: =if(len(A82)>0, VLOOKUP(A82,Lookup!$A$2:$F1000,6,FALSE),"")
C83: =if(len(A83)>0, VLOOKUP(A83,Lookup!$A$2:$F1000,6,FALSE),"")
C84: =if(len(A84)>0, VLOOKUP(A84,Lookup!$A$2:$F1000,6,FALSE),"")
C85: =if(len(A85)>0, VLOOKUP(A85,Lookup!$A$2:$F1000,6,FALSE),"")
C86: =if(len(A86)>0, VLOOKUP(A86,Lookup!$A$2:$F1000,6,FALSE),"")
C87: =if(len(A87)>0, VLOOKUP(A87,Lookup!$A$2:$F1000,6,FALSE),"")
C88: =if(len(A88)>0, VLOOKUP(A88,Lookup!$A$2:$F1000,6,FALSE),"")
C89: =if(len(A89)>0, VLOOKUP(A89,Lookup!$A$2:$F1000,6,FALSE),"")
C90: =if(len(A90)>0, VLOOKUP(A90,Lookup!$A$2:$F1000,6,FALSE),"")
C91: =if(len(A91)>0, VLOOKUP(A91,Lookup!$A$2:$F1000,6,FALSE),"")
C92: =if(len(A92)>0, VLOOKUP(A92,Lookup!$A$2:$F1000,6,FALSE),"")
C93: =if(len(A93)>0, VLOOKUP(A93,Lookup!$A$2:$F1000,6,FALSE),"")
C94: =if(len(A94)>0, VLOOKUP(A94,Lookup!$A$2:$F1000,6,FALSE),"")
C95: =if(len(A95)>0, VLOOKUP(A95,Lookup!$A$2:$F1000,6,FALSE),"")
C96: =if(len(A96)>0, VLOOKUP(A96,Lookup!$A$2:$F1000,6,FALSE),"")
C97: =if(len(A97)>0, VLOOKUP(A97,Lookup!$A$2:$F1000,6,FALSE),"")
C98: =if(len(A98)>0, VLOOKUP(A98,Lookup!$A$2:$F1000,6,FALSE),"")
C99: =if(len(A99)>0, VLOOKUP(A99,Lookup!$A$2:$F1000,6,FALSE),"")
C100: =if(len(A100)>0, VLOOKUP(A100,Lookup!$A$2:$F1000,6,FALSE),"")
...

Sheet TasksToDo
A1: Task # | B1: Task Description | C1: Owner | D1: Start Date | E1: Completed On | F1: Duration | G1: Status | H1: Notes
A2: 1
A3: 2
A4: 3
A5: 4
A6: 5
A7: 6
A8: 7
A9: 8
A10: 9

Sheet Budget
A1: Type | B1: Category | C1: Sub-Category | D1: Amount | E1: PSF | F1: Status
A2: Hard Costs | B2: General Condition | C2: Temp. Facility, Safety, Garbage | D2: 134000 | E2: =D2/Dashboard!$B$3 -> 13.4 | F2: Open
A3: Hard Costs | B3: General Condition | C3: Sidewalk Shed and Scaffolding | D3: 120000 | E3: =D3/Dashboard!$B$3 -> 12 | F3: Open
A4: Hard Costs | B4: General Condition | C4: Direct Labor | D4: 200000 | E4: =D4/Dashboard!$B$3 -> 20 | F4: Open
A5: Hard Costs | B5: Foundation Site Work | C5: Demolition | D5: 225000 | E5: =D5/Dashboard!$B$3 -> 22.5 | F5: Fixed
A6: Hard Costs | B6: Foundation Site Work | C6: Shoring | D6: 190000 | E6: =D6/Dashboard!$B$3 -> 19 | F6: Fixed
A7: Hard Costs | B7: Foundation Site Work | C7: Excavation & Soil Disposal | D7: 220000 | E7: =D7/Dashboard!$B$3 -> 22 | F7: Fixed
A8: Hard Costs | B8: Foundation Site Work | C8: Excavation (Existing Foundation) | D8: 0 | E8: =D8/Dashboard!$B$3 -> 0 | F8: Fixed
A9: Hard Costs | B9: Foundation Site Work | C9: Footings, foundation Walls | D9: 265000 | E9: =D9/Dashboard!$B$3 -> 26.5 | F9: Fixed
A10: Hard Costs | B10: Superstructure | C10: Concrete Superstructure | D10: 935000 | E10: =D10/Dashboard!$B$3 -> 93.5 | F10: Fixed
A11: Hard Costs | B11: Superstructure | C11: Foundation Walls | D11: 50000 | E11: =D11/Dashboard!$B$3 -> 5 | F11: Fixed
A12: Hard Costs | B12: Superstructure | C12: Foundation Slab | D12: 0 | E12: =D12/Dashboard!$B$3 -> 0 | F12: Fixed
A13: Hard Costs | B13: Carpentry | C13: Exterior and Rough Framing | D13: 213000 | E13: =D13/Dashboard!$B$3 -> 21.3 | F13: Fixed
... A65: Soft Costs | B65: Soft Costs | C65: Loan Fee | D65: 21500 | E65: =D65/Dashboard!$B$3 -> 2.15 | F65: Fixed

Sheet Project Plan
B1: Project Ghant Chart
B3: PROJECT TITLE | D3: =Dashboard!B1 -> 219 Driggs Street
B4: GENERAL CONTRACTOR | D4: Renovation Group
B5: PROJECT START DATE | D5: 45413
I6: =E9 -> 45413 | J6: =I6+7 -> 45420 | K6: =J6+7 -> 45427 | L6: =K6+7 -> 45434 | M6: =L6+7 -> 45441 | N6: =M6+7 -> 45448 | O6: =N6+7 -> 45455 | P6: =O6+7 -> 45462 | Q6: =P6+7 -> 45469 | ... ES6: =ER6+7 -> 46393
B7: WBS NUMBER | C7: TASK TITLE | D7: TASK OWNER | E7: START DATE | F7: DUE DATE | G7: DURATION (DAYS) | H7: PCT OF TASK COMPLETE
I8: 1 | J8: =I8+1 -> 2 | K8: =J8+1 -> 3 | L8: =K8+1 -> 4 | M8: =L8+1 -> 5 | N8: =M8+1 -> 6 | O8: =N8+1 -> 7 | P8: =O8+1 -> 8 | Q8: =P8+1 -> 9 | ... ES8: =ER8+1 -> 141
B9: 1 | C9: Planning | E9: =D5 -> 45413 | F9: =max(F10:F24) -> 45688
B10: 2 | C10: Contract Execution | E10: =D5 -> 45413 | F10: =E10+G10 -> 45414 | G10: 1 | H10: 1 | I10: =IF(AND($E10<=I$6,$F10>=I$6),"X","") -> X | J10: =IF(AND($E10<=J$6,$F10>=J$6),"X","") | K10: =IF(AND($E10<=K$6,$F10>=K$6),"X","") | L10: =IF(AND($E10<=L$6,$F10>=L$6),"X","") | M10: =IF(AND($E10<=M$6,$F10>=M$6),"X","") | N10: =IF(AND($E10<=N$6,$F10>=N$6),"X","") | O10: =IF(AND($E10<=O$6,$F10>=O$6),"X","") | P10: =IF(AND($E10<=P$6,$F10>=P$6),"X","") | ... ES10: =IF(AND($E10<=ES$6,$F10>=ES$6),"X","")
B11: 3 | C11: Survey | E11: =E9 -> 45413 | F11: =E11+G11 -> 45434 | G11: 21 | H11: 1 | I11: =IF(AND($E11<=I$6,$F11>=I$6),"X","") -> X | J11: =IF(AND($E11<=J$6,$F11>=J$6),"X","") -> X | K11: =IF(AND($E11<=K$6,$F11>=K$6),"X","") -> X | L11: =IF(AND($E11<=L$6,$F11>=L$6),"X","") -> X | M11: =IF(AND($E11<=M$6,$F11>=M$6),"X","") | N11: =IF(AND($E11<=N$6,$F11>=N$6),"X","") | O11: =IF(AND($E11<=O$6,$F11>=O$6),"X","") | P11: =IF(AND($E11<=P$6,$F11>=P$6),"X","") | ... ES11: =IF(AND($E11<=ES$6,$F11>=ES$6),"X","")
B12: 4 | C12: Environmental | E12: =E9 -> 45413 | F12: =E12+G12 -> 45441 | G12: 28 | H12: 0 | I12: =IF(AND($E12<=I$6,$F12>=I$6),"X","") -> X | J12: =IF(AND($E12<=J$6,$F12>=J$6),"X","") -> X | K12: =IF(AND($E12<=K$6,$F12>=K$6),"X","") -> X | L12: =IF(AND($E12<=L$6,$F12>=L$6),"X","") -> X | M12: =IF(AND($E12<=M$6,$F12>=M$6),"X","") -> X | N12: =IF(AND($E12<=N$6,$F12>=N$6),"X","") | O12: =IF(AND($E12<=O$6,$F12>=O$6),"X","") | P12: =IF(AND($E12<=P$6,$F12>=P$6),"X","") | ... ES12: =IF(AND($E12<=ES$6,$F12>=ES$6),"X","")
B13: 5 | C13: Architectural Engineering Planning | E13: =E12-200 -> 45213 | F13: =E13+G13 -> 45563 | G13: 350 | H13: 0.75 | I13: =IF(AND($E13<=I$6,$F13>=I$6),"X","") -> X | J13: =IF(AND($E13<=J$6,$F13>=J$6),"X","") -> X | K13: =IF(AND($E13<=K$6,$F13>=K$6),"X","") -> X | L13: =IF(AND($E13<=L$6,$F13>=L$6),"X","") -> X | M13: =IF(AND($E13<=M$6,$F13>=M$6),"X","") -> X | N13: =IF(AND($E13<=N$6,$F13>=N$6),"X","") -> X | O13: =IF(AND($E13<=O$6,$F13>=O$6),"X","") -> X | P13: =IF(AND($E13<=P$6,$F13>=P$6),"X","") -> X | ... ES13: =IF(AND($E13<=ES$6,$F13>=ES$6),"X","")
C14: Architectural Plans | E14: 45413 | F14: =E14+G14 -> 45688 | G14: 275 | H14: 0.9 | I14: =IF(AND($E14<=I$6,$F14>=I$6),"X","") -> X | J14: =IF(AND($E14<=J$6,$F14>=J$6),"X","") -> X | K14: =IF(AND($E14<=K$6,$F14>=K$6),"X","") -> X | L14: =IF(AND($E14<=L$6,$F14>=L$6),"X","") -> X | M14: =IF(AND($E14<=M$6,$F14>=M$6),"X","") -> X | N14: =IF(AND($E14<=N$6,$F14>=N$6),"X","") -> X | O14: =IF(AND($E14<=O$6,$F14>=O$6),"X","") -> X | P14: =IF(AND($E14<=P$6,$F14>=P$6),"X","") -> X | ... ES14: =IF(AND($E14<=ES$6,$F14>=ES$6),"X","")
C15: Structural Plans | E15: 45413 | F15: =E15+G15 -> 45688 | G15: 275 | H15: 0.9 | I15: =IF(AND($E15<=I$6,$F15>=I$6),"X","") -> X | J15: =IF(AND($E15<=J$6,$F15>=J$6),"X","") -> X | K15: =IF(AND($E15<=K$6,$F15>=K$6),"X","") -> X | L15: =IF(AND($E15<=L$6,$F15>=L$6),"X","") -> X | M15: =IF(AND($E15<=M$6,$F15>=M$6),"X","") -> X | N15: =IF(AND($E15<=N$6,$F15>=N$6),"X","") -> X | O15: =IF(AND($E15<=O$6,$F15>=O$6),"X","") -> X | P15: =IF(AND($E15<=P$6,$F15>=P$6),"X","") -> X | ... ES15: =IF(AND($E15<=ES$6,$F15>=ES$6),"X","")
C16: Fire Protection Plans (Sprinklers) | E16: 45413 | F16: =E16+G16 -> 45688 | G16: 275 | H16: 0.9 | I16: =IF(AND($E16<=I$6,$F16>=I$6),"X","") -> X | J16: =IF(AND($E16<=J$6,$F16>=J$6),"X","") -> X | K16: =IF(AND($E16<=K$6,$F16>=K$6),"X","") -> X | L16: =IF(AND($E16<=L$6,$F16>=L$6),"X","") -> X | M16: =IF(AND($E16<=M$6,$F16>=M$6),"X","") -> X | N16: =IF(AND($E16<=N$6,$F16>=N$6),"X","") -> X | O16: =IF(AND($E16<=O$6,$F16>=O$6),"X","") -> X | P16: =IF(AND($E16<=P$6,$F16>=P$6),"X","") -> X | ... ES16: =IF(AND($E16<=ES$6,$F16>=ES$6),"X","")
C17: MEP Plans | E17: 45413 | F17: =E17+G17 -> 45688 | G17: 275 | H17: 0.9 | I17: =IF(AND($E17<=I$6,$F17>=I$6),"X","") -> X | J17: =IF(AND($E17<=J$6,$F17>=J$6),"X","") -> X | K17: =IF(AND($E17<=K$6,$F17>=K$6),"X","") -> X | L17: =IF(AND($E17<=L$6,$F17>=L$6),"X","") -> X | M17: =IF(AND($E17<=M$6,$F17>=M$6),"X","") -> X | N17: =IF(AND($E17<=N$6,$F17>=N$6),"X","") -> X | O17: =IF(AND($E17<=O$6,$F17>=O$6),"X","") -> X | P17: =IF(AND($E17<=P$6,$F17>=P$6),"X","") -> X | ... ES17: =IF(AND($E17<=ES$6,$F17>=ES$6),"X","")
C18: Plumbing Plans | E18: 45413 | F18: =E18+G18 -> 45688 | G18: 275 | H18: 0.9 | I18: =IF(AND($E18<=I$6,$F18>=I$6),"X","") -> X | J18: =IF(AND($E18<=J$6,$F18>=J$6),"X","") -> X | K18: =IF(AND($E18<=K$6,$F18>=K$6),"X","") -> X | L18: =IF(AND($E18<=L$6,$F18>=L$6),"X","") -> X | M18: =IF(AND($E18<=M$6,$F18>=M$6),"X","") -> X | N18: =IF(AND($E18<=N$6,$F18>=N$6),"X","") -> X | O18: =IF(AND($E18<=O$6,$F18>=O$6),"X","") -> X | P18: =IF(AND($E18<=P$6,$F18>=P$6),"X","") -> X | ... ES18: =IF(AND($E18<=ES$6,$F18>=ES$6),"X","")
C19: SD1 and SD2 | E19: 45413 | F19: =E19+G19 -> 45688 | G19: 275 | H19: 0.9 | I19: =IF(AND($E19<=I$6,$F19>=I$6),"X","") -> X | J19: =IF(AND($E19<=J$6,$F19>=J$6),"X","") -> X | K19: =IF(AND($E19<=K$6,$F19>=K$6),"X","") -> X | L19: =IF(AND($E19<=L$6,$F19>=L$6),"X","") -> X | M19: =IF(AND($E19<=M$6,$F19>=M$6),"X","") -> X | N19: =IF(AND($E19<=N$6,$F19>=N$6),"X","") -> X | O19: =IF(AND($E19<=O$6,$F19>=O$6),"X","") -> X | P19: =IF(AND($E19<=P$6,$F19>=P$6),"X","") -> X | ... ES19: =IF(AND($E19<=ES$6,$F19>=ES$6),"X","")
B20: 6 | C20: Soil Borings | E20: 45458 | F20: =E20+G20 -> 45486 | G20: 28 | H20: 1 | I20: =IF(AND($E20<=I$6,$F20>=I$6),"X","") | J20: =IF(AND($E20<=J$6,$F20>=J$6),"X","") | K20: =IF(AND($E20<=K$6,$F20>=K$6),"X","") | L20: =IF(AND($E20<=L$6,$F20>=L$6),"X","") | M20: =IF(AND($E20<=M$6,$F20>=M$6),"X","") | N20: =IF(AND($E20<=N$6,$F20>=N$6),"X","") | O20: =IF(AND($E20<=O$6,$F20>=O$6),"X","") | P20: =IF(AND($E20<=P$6,$F20>=P$6),"X","") -> X | ... ES20: =IF(AND($E20<=ES$6,$F20>=ES$6),"X","")
B21: 7 | C21: Demolition Plans | E21: =E9-100 -> 45313 | F21: =E21+G21 -> 45313 | G21: 0 | H21: 1 | I21: =IF(AND($E21<=I$6,$F21>=I$6),"X","") | J21: =IF(AND($E21<=J$6,$F21>=J$6),"X","") | K21: =IF(AND($E21<=K$6,$F21>=K$6),"X","") | L21: =IF(AND($E21<=L$6,$F21>=L$6),"X","") | M21: =IF(AND($E21<=M$6,$F21>=M$6),"X","") | N21: =IF(AND($E21<=N$6,$F21>=N$6),"X","") | O21: =IF(AND($E21<=O$6,$F21>=O$6),"X","") | P21: =IF(AND($E21<=P$6,$F21>=P$6),"X","") | ... ES21: =IF(AND($E21<=ES$6,$F21>=ES$6),"X","")
B22: 8 | C22: Aquisition Financing | E22: =E21 -> 45313 | F22: =E22+G22 -> 45313 | G22: 0 | H22: 1 | I22: =IF(AND($E22<=I$6,$F22>=I$6),"X","") | J22: =IF(AND($E22<=J$6,$F22>=J$6),"X","") | K22: =IF(AND($E22<=K$6,$F22>=K$6),"X","") | L22: =IF(AND($E22<=L$6,$F22>=L$6),"X","") | M22: =IF(AND($E22<=M$6,$F22>=M$6),"X","") | N22: =IF(AND($E22<=N$6,$F22>=N$6),"X","") | O22: =IF(AND($E22<=O$6,$F22>=O$6),"X","") | P22: =IF(AND($E22<=P$6,$F22>=P$6),"X","") | ... ES22: =IF(AND($E22<=ES$6,$F22>=ES$6),"X","")
B23: 9 | C23: Secure Equity | E23: =E10 -> 45413 | F23: =E23+G23 -> 45413 | G23: 0 | H23: 1 | I23: =IF(AND($E23<=I$6,$F23>=I$6),"X","") -> X | J23: =IF(AND($E23<=J$6,$F23>=J$6),"X","") | K23: =IF(AND($E23<=K$6,$F23>=K$6),"X","") | L23: =IF(AND($E23<=L$6,$F23>=L$6),"X","") | M23: =IF(AND($E23<=M$6,$F23>=M$6),"X","") | N23: =IF(AND($E23<=N$6,$F23>=N$6),"X","") | O23: =IF(AND($E23<=O$6,$F23>=O$6),"X","") | P23: =IF(AND($E23<=P$6,$F23>=P$6),"X","") | ... ES23: =IF(AND($E23<=ES$6,$F23>=ES$6),"X","")
B24: 10 | C24: Construction Loan | E24: =F13-10 -> 45553 | F24: =E24+G24 -> 45613 | G24: 60 | H24: 0 | I24: =IF(AND($E24<=I$6,$F24>=I$6),"X","") | J24: =IF(AND($E24<=J$6,$F24>=J$6),"X","") | K24: =IF(AND($E24<=K$6,$F24>=K$6),"X","") | L24: =IF(AND($E24<=L$6,$F24>=L$6),"X","") | M24: =IF(AND($E24<=M$6,$F24>=M$6),"X","") | N24: =IF(AND($E24<=N$6,$F24>=N$6),"X","") | O24: =IF(AND($E24<=O$6,$F24>=O$6),"X","") | P24: =IF(AND($E24<=P$6,$F24>=P$6),"X","") | ... ES24: =IF(AND($E24<=ES$6,$F24>=ES$6),"X","")
B25: 11 | C25: DOB Approvals | E25: =F13 -> 45563 | F25: =E25+G25 -> 45564 | G25: 1 | H25: 0 | I25: =IF(AND($E25<=I$6,$F25>=I$6),"X","") | J25: =IF(AND($E25<=J$6,$F25>=J$6),"X","") | K25: =IF(AND($E25<=K$6,$F25>=K$6),"X","") | L25: =IF(AND($E25<=L$6,$F25>=L$6),"X","") | M25: =IF(AND($E25<=M$6,$F25>=M$6),"X","") | N25: =IF(AND($E25<=N$6,$F25>=N$6),"X","") | O25: =IF(AND($E25<=O$6,$F25>=O$6),"X","") | P25: =IF(AND($E25<=P$6,$F25>=P$6),"X","") | ... ES25: =IF(AND($E25<=ES$6,$F25>=ES$6),"X","")
C26: Architectural Plans
C27: Structural Plans
C28: SD1 and SD2
C29: Fire Protection Plans
C30: DOB Permits (BIN: 3811217)
C31: Fence Permit
C32: Demolition Permit
C33: New Building Permit
C34: Plumbing Permit
C35: Electrical Permit
B36: 12 | C36: Access Agreements | E36: =E12 -> 45413 | F36: =E36+G36 -> 45613 | G36: 200 | H36: 0 | I36: =IF(AND($E36<=I$6,$F36>=I$6),"X","") -> X | J36: =IF(AND($E36<=J$6,$F36>=J$6),"X","") -> X | K36: =IF(AND($E36<=K$6,$F36>=K$6),"X","") -> X | L36: =IF(AND($E36<=L$6,$F36>=L$6),"X","") -> X | M36: =IF(AND($E36<=M$6,$F36>=M$6),"X","") -> X | N36: =IF(AND($E36<=N$6,$F36>=N$6),"X","") -> X | O36: =IF(AND($E36<=O$6,$F36>=O$6),"X","") -> X | P36: =IF(AND($E36<=P$6,$F36>=P$6),"X","") -> X | ... ES36: =IF(AND($E36<=ES$6,$F36>=ES$6),"X","")
B37: 13 | C37: Project Definition and Planning | E37: =min(E38:E41) -> 45564 | F37: =max(F38:F41) -> 45694
B38: 14 | C38: Demolition | E38: =F36 -> 45613 | F38: =E38+G38 -> 45613 | G38: 0 | H38: 1 | I38: =IF(AND($E38<=I$6,$F38>=I$6),"X","") | J38: =IF(AND($E38<=J$6,$F38>=J$6),"X","") | K38: =IF(AND($E38<=K$6,$F38>=K$6),"X","") | L38: =IF(AND($E38<=L$6,$F38>=L$6),"X","") | M38: =IF(AND($E38<=M$6,$F38>=M$6),"X","") | N38: =IF(AND($E38<=N$6,$F38>=N$6),"X","") | O38: =IF(AND($E38<=O$6,$F38>=O$6),"X","") | P38: =IF(AND($E38<=P$6,$F38>=P$6),"X","") | ... ES38: =IF(AND($E38<=ES$6,$F38>=ES$6),"X","")
B39: 15 | C39: Excavation / Shoring / Foundation | E39: =F25 -> 45564 | F39: =E39+G39 -> 45634 | G39: 70 | H39: 0 | I39: =IF(AND($E39<=I$6,$F39>=I$6),"X","") | J39: =IF(AND($E39<=J$6,$F39>=J$6),"X","") | K39: =IF(AND($E39<=K$6,$F39>=K$6),"X","") | L39: =IF(AND($E39<=L$6,$F39>=L$6),"X","") | M39: =IF(AND($E39<=M$6,$F39>=M$6),"X","") | N39: =IF(AND($E39<=N$6,$F39>=N$6),"X","") | O39: =IF(AND($E39<=O$6,$F39>=O$6),"X","") | P39: =IF(AND($E39<=P$6,$F39>=P$6),"X","") | ... ES39: =IF(AND($E39<=ES$6,$F39>=ES$6),"X","")
B40: 16 | C40: Water Proofing & Concrete Insulation | E40: =E39 -> 45564 | F40: =E40+G40 -> 45594 | G40: 30 | H40: 0 | I40: =IF(AND($E40<=I$6,$F40>=I$6),"X","") | J40: =IF(AND($E40<=J$6,$F40>=J$6),"X","") | K40: =IF(AND($E40<=K$6,$F40>=K$6),"X","") | L40: =IF(AND($E40<=L$6,$F40>=L$6),"X","") | M40: =IF(AND($E40<=M$6,$F40>=M$6),"X","") | N40: =IF(AND($E40<=N$6,$F40>=N$6),"X","") | O40: =IF(AND($E40<=O$6,$F40>=O$6),"X","") | P40: =IF(AND($E40<=P$6,$F40>=P$6),"X","") | ... ES40: =IF(AND($E40<=ES$6,$F40>=ES$6),"X","")
B41: 17 | C41: Super Structure | E41: =F39 -> 45634 | F41: =E41+G41 -> 45694 | G41: 60 | H41: 0 | I41: =IF(AND($E41<=I$6,$F41>=I$6),"X","") | J41: =IF(AND($E41<=J$6,$F41>=J$6),"X","") | K41: =IF(AND($E41<=K$6,$F41>=K$6),"X","") | L41: =IF(AND($E41<=L$6,$F41>=L$6),"X","") | M41: =IF(AND($E41<=M$6,$F41>=M$6),"X","") | N41: =IF(AND($E41<=N$6,$F41>=N$6),"X","") | O41: =IF(AND($E41<=O$6,$F41>=O$6),"X","") | P41: =IF(AND($E41<=P$6,$F41>=P$6),"X","") | ... ES41: =IF(AND($E41<=ES$6,$F41>=ES$6),"X","")
B42: 18 | C42: CMU | E42: =E41+21 -> 45655 | F42: =E42+G42 -> 45745 | G42: 90 | H42: 0 | I42: =IF(AND($E42<=I$6,$F42>=I$6),"X","") | J42: =IF(AND($E42<=J$6,$F42>=J$6),"X","") | K42: =IF(AND($E42<=K$6,$F42>=K$6),"X","") | L42: =IF(AND($E42<=L$6,$F42>=L$6),"X","") | M42: =IF(AND($E42<=M$6,$F42>=M$6),"X","") | N42: =IF(AND($E42<=N$6,$F42>=N$6),"X","") | O42: =IF(AND($E42<=O$6,$F42>=O$6),"X","") | P42: =IF(AND($E42<=P$6,$F42>=P$6),"X","") | ... ES42: =IF(AND($E42<=ES$6,$F42>=ES$6),"X","")
B43: 19 | C43: Elevator | E43: =F42+30 -> 45775 | F43: =E43+G43 -> 45925 | G43: 150 | H43: 0 | I43: =IF(AND($E43<=I$6,$F43>=I$6),"X","") | J43: =IF(AND($E43<=J$6,$F43>=J$6),"X","") | K43: =IF(AND($E43<=K$6,$F43>=K$6),"X","") | L43: =IF(AND($E43<=L$6,$F43>=L$6),"X","") | M43: =IF(AND($E43<=M$6,$F43>=M$6),"X","") | N43: =IF(AND($E43<=N$6,$F43>=N$6),"X","") | O43: =IF(AND($E43<=O$6,$F43>=O$6),"X","") | P43: =IF(AND($E43<=P$6,$F43>=P$6),"X","") | ... ES43: =IF(AND($E43<=ES$6,$F43>=ES$6),"X","")
B44: 20 | C44: Exterior Framing | E44: =E41+30 -> 45664 | F44: =E44+G44 -> 45739 | G44: 75 | H44: 0 | I44: =IF(AND($E44<=I$6,$F44>=I$6),"X","") | J44: =IF(AND($E44<=J$6,$F44>=J$6),"X","") | K44: =IF(AND($E44<=K$6,$F44>=K$6),"X","") | L44: =IF(AND($E44<=L$6,$F44>=L$6),"X","") | M44: =IF(AND($E44<=M$6,$F44>=M$6),"X","") | N44: =IF(AND($E44<=N$6,$F44>=N$6),"X","") | O44: =IF(AND($E44<=O$6,$F44>=O$6),"X","") | P44: =IF(AND($E44<=P$6,$F44>=P$6),"X","") | ... ES44: =IF(AND($E44<=ES$6,$F44>=ES$6),"X","")
B45: 21 | C45: Water Proofing Facade | E45: =F44 -> 45739 | F45: =E45+G45 -> 45753 | G45: 14 | H45: 0 | I45: =IF(AND($E45<=I$6,$F45>=I$6),"X","") | J45: =IF(AND($E45<=J$6,$F45>=J$6),"X","") | K45: =IF(AND($E45<=K$6,$F45>=K$6),"X","") | L45: =IF(AND($E45<=L$6,$F45>=L$6),"X","") | M45: =IF(AND($E45<=M$6,$F45>=M$6),"X","") | N45: =IF(AND($E45<=N$6,$F45>=N$6),"X","") | O45: =IF(AND($E45<=O$6,$F45>=O$6),"X","") | P45: =IF(AND($E45<=P$6,$F45>=P$6),"X","") | ... ES45: =IF(AND($E45<=ES$6,$F45>=ES$6),"X","")
B46: 22 | C46: Installation Exterior Doors / Windows | E46: =F45 -> 45753 | F46: =E46+G46 -> 45767 | G46: 14 | H46: 0 | I46: =IF(AND($E46<=I$6,$F46>=I$6),"X","") | J46: =IF(AND($E46<=J$6,$F46>=J$6),"X","") | K46: =IF(AND($E46<=K$6,$F46>=K$6),"X","") | L46: =IF(AND($E46<=L$6,$F46>=L$6),"X","") | M46: =IF(AND($E46<=M$6,$F46>=M$6),"X","") | N46: =IF(AND($E46<=N$6,$F46>=N$6),"X","") | O46: =IF(AND($E46<=O$6,$F46>=O$6),"X","") | P46: =IF(AND($E46<=P$6,$F46>=P$6),"X","") | ... ES46: =IF(AND($E46<=ES$6,$F46>=ES$6),"X","")
B47: 23 | C47: Masonry Work Brick | E47: =F46 -> 45767 | F47: =E47+G47 -> 45857 | G47: 90 | H47: 0 | I47: =IF(AND($E47<=I$6,$F47>=I$6),"X","") | J47: =IF(AND($E47<=J$6,$F47>=J$6),"X","") | K47: =IF(AND($E47<=K$6,$F47>=K$6),"X","") | L47: =IF(AND($E47<=L$6,$F47>=L$6),"X","") | M47: =IF(AND($E47<=M$6,$F47>=M$6),"X","") | N47: =IF(AND($E47<=N$6,$F47>=N$6),"X","") | O47: =IF(AND($E47<=O$6,$F47>=O$6),"X","") | P47: =IF(AND($E47<=P$6,$F47>=P$6),"X","") | ... ES47: =IF(AND($E47<=ES$6,$F47>=ES$6),"X","")
B48: 24 | C48: Roofing | E48: =F47 -> 45857 | F48: =E48+G48 -> 45977 | G48: 120 | H48: 0 | I48: =IF(AND($E48<=I$6,$F48>=I$6),"X","") | J48: =IF(AND($E48<=J$6,$F48>=J$6),"X","") | K48: =IF(AND($E48<=K$6,$F48>=K$6),"X","") | L48: =IF(AND($E48<=L$6,$F48>=L$6),"X","") | M48: =IF(AND($E48<=M$6,$F48>=M$6),"X","") | N48: =IF(AND($E48<=N$6,$F48>=N$6),"X","") | O48: =IF(AND($E48<=O$6,$F48>=O$6),"X","") | P48: =IF(AND($E48<=P$6,$F48>=P$6),"X","") | ... ES48: =IF(AND($E48<=ES$6,$F48>=ES$6),"X","")
B49: 25 | C49: Interior Framing | E49: =F44 -> 45739 | F49: =E49+G49 -> 45799 | G49: 60 | H49: 0 | I49: =IF(AND($E49<=I$6,$F49>=I$6),"X","") | J49: =IF(AND($E49<=J$6,$F49>=J$6),"X","") | K49: =IF(AND($E49<=K$6,$F49>=K$6),"X","") | L49: =IF(AND($E49<=L$6,$F49>=L$6),"X","") | M49: =IF(AND($E49<=M$6,$F49>=M$6),"X","") | N49: =IF(AND($E49<=N$6,$F49>=N$6),"X","") | O49: =IF(AND($E49<=O$6,$F49>=O$6),"X","") | P49: =IF(AND($E49<=P$6,$F49>=P$6),"X","") | ... ES49: =IF(AND($E49<=ES$6,$F49>=ES$6),"X","")
B50: 26 | C50: Insulation | E50: =F49 -> 45799 | F50: =E50+G50 -> 45814 | G50: 15 | H50: 0 | I50: =IF(AND($E50<=I$6,$F50>=I$6),"X","") | J50: =IF(AND($E50<=J$6,$F50>=J$6),"X","") | K50: =IF(AND($E50<=K$6,$F50>=K$6),"X","") | L50: =IF(AND($E50<=L$6,$F50>=L$6),"X","") | M50: =IF(AND($E50<=M$6,$F50>=M$6),"X","") | N50: =IF(AND($E50<=N$6,$F50>=N$6),"X","") | O50: =IF(AND($E50<=O$6,$F50>=O$6),"X","") | P50: =IF(AND($E50<=P$6,$F50>=P$6),"X","") | ... ES50: =IF(AND($E50<=ES$6,$F50>=ES$6),"X","")
B51: 27 | C51: Plumbing | E51: =E49+10 -> 45749 | F51: =E51+G51 -> 45899 | G51: 150 | H51: 0 | I51: =IF(AND($E51<=I$6,$F51>=I$6),"X","") | J51: =IF(AND($E51<=J$6,$F51>=J$6),"X","") | K51: =IF(AND($E51<=K$6,$F51>=K$6),"X","") | L51: =IF(AND($E51<=L$6,$F51>=L$6),"X","") | M51: =IF(AND($E51<=M$6,$F51>=M$6),"X","") | N51: =IF(AND($E51<=N$6,$F51>=N$6),"X","") | O51: =IF(AND($E51<=O$6,$F51>=O$6),"X","") | P51: =IF(AND($E51<=P$6,$F51>=P$6),"X","") | ... ES51: =IF(AND($E51<=ES$6,$F51>=ES$6),"X","")
B52: 28 | C52: Sprinkler | E52: =F49 -> 45799 | F52: =E52+G52 -> 45848 | G52: 49 | H52: 0 | I52: =IF(AND($E52<=I$6,$F52>=I$6),"X","") | J52: =IF(AND($E52<=J$6,$F52>=J$6),"X","") | K52: =IF(AND($E52<=K$6,$F52>=K$6),"X","") | L52: =IF(AND($E52<=L$6,$F52>=L$6),"X","") | M52: =IF(AND($E52<=M$6,$F52>=M$6),"X","") | N52: =IF(AND($E52<=N$6,$F52>=N$6),"X","") | O52: =IF(AND($E52<=O$6,$F52>=O$6),"X","") | P52: =IF(AND($E52<=P$6,$F52>=P$6),"X","") | ... ES52: =IF(AND($E52<=ES$6,$F52>=ES$6),"X","")
B53: 29 | C53: Electrical | E53: =F49 -> 45799 | F53: =E53+G53 -> 45919 | G53: 120 | H53: 0 | I53: =IF(AND($E53<=I$6,$F53>=I$6),"X","") | J53: =IF(AND($E53<=J$6,$F53>=J$6),"X","") | K53: =IF(AND($E53<=K$6,$F53>=K$6),"X","") | L53: =IF(AND($E53<=L$6,$F53>=L$6),"X","") | M53: =IF(AND($E53<=M$6,$F53>=M$6),"X","") | N53: =IF(AND($E53<=N$6,$F53>=N$6),"X","") | O53: =IF(AND($E53<=O$6,$F53>=O$6),"X","") | P53: =IF(AND($E53<=P$6,$F53>=P$6),"X","") | ... ES53: =IF(AND($E53<=ES$6,$F53>=ES$6),"X","")
B54: 30 | C54: Fire Alarm | E54: =F49 -> 45799 | F54: =E54+G54 -> 45899 | G54: 100 | H54: 0 | I54: =IF(AND($E54<=I$6,$F54>=I$6),"X","") | J54: =IF(AND($E54<=J$6,$F54>=J$6),"X","") | K54: =IF(AND($E54<=K$6,$F54>=K$6),"X","") | L54: =IF(AND($E54<=L$6,$F54>=L$6),"X","") | M54: =IF(AND($E54<=M$6,$F54>=M$6),"X","") | N54: =IF(AND($E54<=N$6,$F54>=N$6),"X","") | O54: =IF(AND($E54<=O$6,$F54>=O$6),"X","") | P54: =IF(AND($E54<=P$6,$F54>=P$6),"X","") | ... ES54: =IF(AND($E54<=ES$6,$F54>=ES$6),"X","")
B55: 31 | C55: Low Voltage | E55: =F53 -> 45919 | F55: =E55+G55 -> 45933 | G55: 14 | H55: 0 | I55: =IF(AND($E55<=I$6,$F55>=I$6),"X","") | J55: =IF(AND($E55<=J$6,$F55>=J$6),"X","") | K55: =IF(AND($E55<=K$6,$F55>=K$6),"X","") | L55: =IF(AND($E55<=L$6,$F55>=L$6),"X","") | M55: =IF(AND($E55<=M$6,$F55>=M$6),"X","") | N55: =IF(AND($E55<=N$6,$F55>=N$6),"X","") | O55: =IF(AND($E55<=O$6,$F55>=O$6),"X","") | P55: =IF(AND($E55<=P$6,$F55>=P$6),"X","") | ... ES55: =IF(AND($E55<=ES$6,$F55>=ES$6),"X","")
B56: 32 | C56: AC | E56: =F49 -> 45799 | F56: =E56+G56 -> 45899 | G56: 100 | H56: 0 | I56: =IF(AND($E56<=I$6,$F56>=I$6),"X","") | J56: =IF(AND($E56<=J$6,$F56>=J$6),"X","") | K56: =IF(AND($E56<=K$6,$F56>=K$6),"X","") | L56: =IF(AND($E56<=L$6,$F56>=L$6),"X","") | M56: =IF(AND($E56<=M$6,$F56>=M$6),"X","") | N56: =IF(AND($E56<=N$6,$F56>=N$6),"X","") | O56: =IF(AND($E56<=O$6,$F56>=O$6),"X","") | P56: =IF(AND($E56<=P$6,$F56>=P$6),"X","") | ... ES56: =IF(AND($E56<=ES$6,$F56>=ES$6),"X","")
B57: 33 | C57: Sheetrock | E57: =F49 -> 45799 | F57: =E57+G57 -> 45834 | G57: 35 | H57: 0 | I57: =IF(AND($E57<=I$6,$F57>=I$6),"X","") | J57: =IF(AND($E57<=J$6,$F57>=J$6),"X","") | K57: =IF(AND($E57<=K$6,$F57>=K$6),"X","") | L57: =IF(AND($E57<=L$6,$F57>=L$6),"X","") | M57: =IF(AND($E57<=M$6,$F57>=M$6),"X","") | N57: =IF(AND($E57<=N$6,$F57>=N$6),"X","") | O57: =IF(AND($E57<=O$6,$F57>=O$6),"X","") | P57: =IF(AND($E57<=P$6,$F57>=P$6),"X","") | ... ES57: =IF(AND($E57<=ES$6,$F57>=ES$6),"X","")
B58: 34 | C58: Plaster & Primer | E58: =F57 -> 45834 | F58: =E58+G58 -> 45862 | G58: 28 | H58: 0 | I58: =IF(AND($E58<=I$6,$F58>=I$6),"X","") | J58: =IF(AND($E58<=J$6,$F58>=J$6),"X","") | K58: =IF(AND($E58<=K$6,$F58>=K$6),"X","") | L58: =IF(AND($E58<=L$6,$F58>=L$6),"X","") | M58: =IF(AND($E58<=M$6,$F58>=M$6),"X","") | N58: =IF(AND($E58<=N$6,$F58>=N$6),"X","") | O58: =IF(AND($E58<=O$6,$F58>=O$6),"X","") | P58: =IF(AND($E58<=P$6,$F58>=P$6),"X","") | ... ES58: =IF(AND($E58<=ES$6,$F58>=ES$6),"X","")
B59: 35 | C59: Tiles | E59: =max(F51,F57)-30 -> 45869 | F59: =E59+G59 -> 45899 | G59: 30 | H59: 0 | I59: =IF(AND($E59<=I$6,$F59>=I$6),"X","") | J59: =IF(AND($E59<=J$6,$F59>=J$6),"X","") | K59: =IF(AND($E59<=K$6,$F59>=K$6),"X","") | L59: =IF(AND($E59<=L$6,$F59>=L$6),"X","") | M59: =IF(AND($E59<=M$6,$F59>=M$6),"X","") | N59: =IF(AND($E59<=N$6,$F59>=N$6),"X","") | O59: =IF(AND($E59<=O$6,$F59>=O$6),"X","") | P59: =IF(AND($E59<=P$6,$F59>=P$6),"X","") | ... ES59: =IF(AND($E59<=ES$6,$F59>=ES$6),"X","")
B60: 36 | C60: Floors | E60: =F59-14 -> 45885 | F60: =E60+G60 -> 45913 | G60: 28 | H60: 0 | I60: =IF(AND($E60<=I$6,$F60>=I$6),"X","") | J60: =IF(AND($E60<=J$6,$F60>=J$6),"X","") | K60: =IF(AND($E60<=K$6,$F60>=K$6),"X","") | L60: =IF(AND($E60<=L$6,$F60>=L$6),"X","") | M60: =IF(AND($E60<=M$6,$F60>=M$6),"X","") | N60: =IF(AND($E60<=N$6,$F60>=N$6),"X","") | O60: =IF(AND($E60<=O$6,$F60>=O$6),"X","") | P60: =IF(AND($E60<=P$6,$F60>=P$6),"X","") | ... ES60: =IF(AND($E60<=ES$6,$F60>=ES$6),"X","")
B61: 37 | C61: Carpentry | E61: =E59+14 -> 45883 | F61: =E61+G61 -> 45946 | G61: 63 | H61: 0 | I61: =IF(AND($E61<=I$6,$F61>=I$6),"X","") | J61: =IF(AND($E61<=J$6,$F61>=J$6),"X","") | K61: =IF(AND($E61<=K$6,$F61>=K$6),"X","") | L61: =IF(AND($E61<=L$6,$F61>=L$6),"X","") | M61: =IF(AND($E61<=M$6,$F61>=M$6),"X","") | N61: =IF(AND($E61<=N$6,$F61>=N$6),"X","") | O61: =IF(AND($E61<=O$6,$F61>=O$6),"X","") | P61: =IF(AND($E61<=P$6,$F61>=P$6),"X","") | ... ES61: =IF(AND($E61<=ES$6,$F61>=ES$6),"X","")
B62: 38 | C62: Interior Doors | E62: =F60 -> 45913 | F62: =E62+G62 -> 45943 | G62: 30 | H62: 0 | I62: =IF(AND($E62<=I$6,$F62>=I$6),"X","") | J62: =IF(AND($E62<=J$6,$F62>=J$6),"X","") | K62: =IF(AND($E62<=K$6,$F62>=K$6),"X","") | L62: =IF(AND($E62<=L$6,$F62>=L$6),"X","") | M62: =IF(AND($E62<=M$6,$F62>=M$6),"X","") | N62: =IF(AND($E62<=N$6,$F62>=N$6),"X","") | O62: =IF(AND($E62<=O$6,$F62>=O$6),"X","") | P62: =IF(AND($E62<=P$6,$F62>=P$6),"X","") | ... ES62: =IF(AND($E62<=ES$6,$F62>=ES$6),"X","")
B63: 39 | C63: Kitchen Cabinetry | E63: =F60 -> 45913 | F63: =E63+G63 -> 45955 | G63: 42 | H63: 0 | I63: =IF(AND($E63<=I$6,$F63>=I$6),"X","") | J63: =IF(AND($E63<=J$6,$F63>=J$6),"X","") | K63: =IF(AND($E63<=K$6,$F63>=K$6),"X","") | L63: =IF(AND($E63<=L$6,$F63>=L$6),"X","") | M63: =IF(AND($E63<=M$6,$F63>=M$6),"X","") | N63: =IF(AND($E63<=N$6,$F63>=N$6),"X","") | O63: =IF(AND($E63<=O$6,$F63>=O$6),"X","") | P63: =IF(AND($E63<=P$6,$F63>=P$6),"X","") | ... ES63: =IF(AND($E63<=ES$6,$F63>=ES$6),"X","")
B64: 40 | C64: Bathroom Fixtures | E64: =F59 -> 45899 | F64: =E64+G64 -> 45913 | G64: 14 | H64: 0 | I64: =IF(AND($E64<=I$6,$F64>=I$6),"X","") | J64: =IF(AND($E64<=J$6,$F64>=J$6),"X","") | K64: =IF(AND($E64<=K$6,$F64>=K$6),"X","") | L64: =IF(AND($E64<=L$6,$F64>=L$6),"X","") | M64: =IF(AND($E64<=M$6,$F64>=M$6),"X","") | N64: =IF(AND($E64<=N$6,$F64>=N$6),"X","") | O64: =IF(AND($E64<=O$6,$F64>=O$6),"X","") | P64: =IF(AND($E64<=P$6,$F64>=P$6),"X","") | ... ES64: =IF(AND($E64<=ES$6,$F64>=ES$6),"X","")
B65: 41 | C65: Shower Doors | E65: =F64 -> 45913 | F65: =E65+G65 -> 45927 | G65: 14 | H65: 0 | I65: =IF(AND($E65<=I$6,$F65>=I$6),"X","") | J65: =IF(AND($E65<=J$6,$F65>=J$6),"X","") | K65: =IF(AND($E65<=K$6,$F65>=K$6),"X","") | L65: =IF(AND($E65<=L$6,$F65>=L$6),"X","") | M65: =IF(AND($E65<=M$6,$F65>=M$6),"X","") | N65: =IF(AND($E65<=N$6,$F65>=N$6),"X","") | O65: =IF(AND($E65<=O$6,$F65>=O$6),"X","") | P65: =IF(AND($E65<=P$6,$F65>=P$6),"X","") | ... ES65: =IF(AND($E65<=ES$6,$F65>=ES$6),"X","")
B66: 42 | C66: Paintinng | E66: =max(F57:F61) -> 45946 | F66: =E66+G66 -> 45981 | G66: 35 | H66: 0 | I66: =IF(AND($E66<=I$6,$F66>=I$6),"X","") | J66: =IF(AND($E66<=J$6,$F66>=J$6),"X","") | K66: =IF(AND($E66<=K$6,$F66>=K$6),"X","") | L66: =IF(AND($E66<=L$6,$F66>=L$6),"X","") | M66: =IF(AND($E66<=M$6,$F66>=M$6),"X","") | N66: =IF(AND($E66<=N$6,$F66>=N$6),"X","") | O66: =IF(AND($E66<=O$6,$F66>=O$6),"X","") | P66: =IF(AND($E66<=P$6,$F66>=P$6),"X","") | ... ES66: =IF(AND($E66<=ES$6,$F66>=ES$6),"X","")
B67: 43 | C67: Sidewalk and Asphalt for BPP | E67: =max(F49:F61) -> 45946 | F67: =E67+G67 -> 45976 | G67: 30 | H67: 0 | I67: =IF(AND($E67<=I$6,$F67>=I$6),"X","") | J67: =IF(AND($E67<=J$6,$F67>=J$6),"X","") | K67: =IF(AND($E67<=K$6,$F67>=K$6),"X","") | L67: =IF(AND($E67<=L$6,$F67>=L$6),"X","") | M67: =IF(AND($E67<=M$6,$F67>=M$6),"X","") | N67: =IF(AND($E67<=N$6,$F67>=N$6),"X","") | O67: =IF(AND($E67<=O$6,$F67>=O$6),"X","") | P67: =IF(AND($E67<=P$6,$F67>=P$6),"X","") | ... ES67: =IF(AND($E67<=ES$6,$F67>=ES$6),"X","")
B68: 44 | C68: Sign Off / Misc / Touch ups | E68: =E67 -> 45946 | F68: =E68+G68 -> 46036 | G68: 90 | H68: 0 | I68: =IF(AND($E68<=I$6,$F68>=I$6),"X","") | J68: =IF(AND($E68<=J$6,$F68>=J$6),"X","") | K68: =IF(AND($E68<=K$6,$F68>=K$6),"X","") | L68: =IF(AND($E68<=L$6,$F68>=L$6),"X","") | M68: =IF(AND($E68<=M$6,$F68>=M$6),"X","") | N68: =IF(AND($E68<=N$6,$F68>=N$6),"X","") | O68: =IF(AND($E68<=O$6,$F68>=O$6),"X","") | P68: =IF(AND($E68<=P$6,$F68>=P$6),"X","") | ... ES68: =IF(AND($E68<=ES$6,$F68>=ES$6),"X","")
B69: 45 | I69: =IF(AND($E69<=I$6,$F69>=I$6),"X","") | J69: =IF(AND($E69<=J$6,$F69>=J$6),"X","") | K69: =IF(AND($E69<=K$6,$F69>=K$6),"X","") | L69: =IF(AND($E69<=L$6,$F69>=L$6),"X","") | M69: =IF(AND($E69<=M$6,$F69>=M$6),"X","") | N69: =IF(AND($E69<=N$6,$F69>=N$6),"X","") | O69: =IF(AND($E69<=O$6,$F69>=O$6),"X","") | P69: =IF(AND($E69<=P$6,$F69>=P$6),"X","") | ... ES69: =IF(AND($E69<=ES$6,$F69>=ES$6),"X","")
B70: 46 | I70: =IF(AND($E70<=I$6,$F70>=I$6),"X","") | J70: =IF(AND($E70<=J$6,$F70>=J$6),"X","") | K70: =IF(AND($E70<=K$6,$F70>=K$6),"X","") | L70: =IF(AND($E70<=L$6,$F70>=L$6),"X","") | M70: =IF(AND($E70<=M$6,$F70>=M$6),"X","") | N70: =IF(AND($E70<=N$6,$F70>=N$6),"X","") | O70: =IF(AND($E70<=O$6,$F70>=O$6),"X","") | P70: =IF(AND($E70<=P$6,$F70>=P$6),"X","") | ... ES70: =IF(AND($E70<=ES$6,$F70>=ES$6),"X","")
B71: 47 | I71: =IF(AND($E71<=I$6,$F71>=I$6),"X","") | J71: =IF(AND($E71<=J$6,$F71>=J$6),"X","") | K71: =IF(AND($E71<=K$6,$F71>=K$6),"X","") | L71: =IF(AND($E71<=L$6,$F71>=L$6),"X","") | M71: =IF(AND($E71<=M$6,$F71>=M$6),"X","") | N71: =IF(AND($E71<=N$6,$F71>=N$6),"X","") | O71: =IF(AND($E71<=O$6,$F71>=O$6),"X","") | P71: =IF(AND($E71<=P$6,$F71>=P$6),"X","") | ... ES71: =IF(AND($E71<=ES$6,$F71>=ES$6),"X","")
B72: 48 | I72: =IF(AND($E72<=I$6,$F72>=I$6),"X","") | J72: =IF(AND($E72<=J$6,$F72>=J$6),"X","") | K72: =IF(AND($E72<=K$6,$F72>=K$6),"X","") | L72: =IF(AND($E72<=L$6,$F72>=L$6),"X","") | M72: =IF(AND($E72<=M$6,$F72>=M$6),"X","") | N72: =IF(AND($E72<=N$6,$F72>=N$6),"X","") | O72: =IF(AND($E72<=O$6,$F72>=O$6),"X","") | P72: =IF(AND($E72<=P$6,$F72>=P$6),"X","") | ... ES72: =IF(AND($E72<=ES$6,$F72>=ES$6),"X","")
B73: 49 | I73: =IF(AND($E73<=I$6,$F73>=I$6),"X","") | J73: =IF(AND($E73<=J$6,$F73>=J$6),"X","") | K73: =IF(AND($E73<=K$6,$F73>=K$6),"X","") | L73: =IF(AND($E73<=L$6,$F73>=L$6),"X","") | M73: =IF(AND($E73<=M$6,$F73>=M$6),"X","") | N73: =IF(AND($E73<=N$6,$F73>=N$6),"X","") | O73: =IF(AND($E73<=O$6,$F73>=O$6),"X","") | P73: =IF(AND($E73<=P$6,$F73>=P$6),"X","") | ... ES73: =IF(AND($E73<=ES$6,$F73>=ES$6),"X","")
B74: 50 | I74: =IF(AND($E74<=I$6,$F74>=I$6),"X","") | J74: =IF(AND($E74<=J$6,$F74>=J$6),"X","") | K74: =IF(AND($E74<=K$6,$F74>=K$6),"X","") | L74: =IF(AND($E74<=L$6,$F74>=L$6),"X","") | M74: =IF(AND($E74<=M$6,$F74>=M$6),"X","") | N74: =IF(AND($E74<=N$6,$F74>=N$6),"X","") | O74: =IF(AND($E74<=O$6,$F74>=O$6),"X","") | P74: =IF(AND($E74<=P$6,$F74>=P$6),"X","") | ... ES74: =IF(AND($E74<=ES$6,$F74>=ES$6),"X","")
B75: 51 | I75: =IF(AND($E75<=I$6,$F75>=I$6),"X","") | J75: =IF(AND($E75<=J$6,$F75>=J$6),"X","") | K75: =IF(AND($E75<=K$6,$F75>=K$6),"X","") | L75: =IF(AND($E75<=L$6,$F75>=L$6),"X","") | M75: =IF(AND($E75<=M$6,$F75>=M$6),"X","") | N75: =IF(AND($E75<=N$6,$F75>=N$6),"X","") | O75: =IF(AND($E75<=O$6,$F75>=O$6),"X","") | P75: =IF(AND($E75<=P$6,$F75>=P$6),"X","") | ... ES75: =IF(AND($E75<=ES$6,$F75>=ES$6),"X","")
B76: 52 | I76: =IF(AND($E76<=I$6,$F76>=I$6),"X","") | J76: =IF(AND($E76<=J$6,$F76>=J$6),"X","") | K76: =IF(AND($E76<=K$6,$F76>=K$6),"X","") | L76: =IF(AND($E76<=L$6,$F76>=L$6),"X","") | M76: =IF(AND($E76<=M$6,$F76>=M$6),"X","") | N76: =IF(AND($E76<=N$6,$F76>=N$6),"X","") | O76: =IF(AND($E76<=O$6,$F76>=O$6),"X","") | P76: =IF(AND($E76<=P$6,$F76>=P$6),"X","") | ... ES76: =IF(AND($E76<=ES$6,$F76>=ES$6),"X","")
B77: 53 | I77: =IF(AND($E77<=I$6,$F77>=I$6),"X","") | J77: =IF(AND($E77<=J$6,$F77>=J$6),"X","") | K77: =IF(AND($E77<=K$6,$F77>=K$6),"X","") | L77: =IF(AND($E77<=L$6,$F77>=L$6),"X","") | M77: =IF(AND($E77<=M$6,$F77>=M$6),"X","") | N77: =IF(AND($E77<=N$6,$F77>=N$6),"X","") | O77: =IF(AND($E77<=O$6,$F77>=O$6),"X","") | P77: =IF(AND($E77<=P$6,$F77>=P$6),"X","") | ... ES77: =IF(AND($E77<=ES$6,$F77>=ES$6),"X","")
B78: 54 | I78: =IF(AND($E78<=I$6,$F78>=I$6),"X","") | J78: =IF(AND($E78<=J$6,$F78>=J$6),"X","") | K78: =IF(AND($E78<=K$6,$F78>=K$6),"X","") | L78: =IF(AND($E78<=L$6,$F78>=L$6),"X","") | M78: =IF(AND($E78<=M$6,$F78>=M$6),"X","") | N78: =IF(AND($E78<=N$6,$F78>=N$6),"X","") | O78: =IF(AND($E78<=O$6,$F78>=O$6),"X","") | P78: =IF(AND($E78<=P$6,$F78>=P$6),"X","") | ... ES78: =IF(AND($E78<=ES$6,$F78>=ES$6),"X","")
B79: 55 | I79: =IF(AND($E79<=I$6,$F79>=I$6),"X","") | J79: =IF(AND($E79<=J$6,$F79>=J$6),"X","") | K79: =IF(AND($E79<=K$6,$F79>=K$6),"X","") | L79: =IF(AND($E79<=L$6,$F79>=L$6),"X","") | M79: =IF(AND($E79<=M$6,$F79>=M$6),"X","") | N79: =IF(AND($E79<=N$6,$F79>=N$6),"X","") | O79: =IF(AND($E79<=O$6,$F79>=O$6),"X","") | P79: =IF(AND($E79<=P$6,$F79>=P$6),"X","") | ... ES79: =IF(AND($E79<=ES$6,$F79>=ES$6),"X","")
B80: 56 | I80: =IF(AND($E80<=I$6,$F80>=I$6),"X","") | J80: =IF(AND($E80<=J$6,$F80>=J$6),"X","") | K80: =IF(AND($E80<=K$6,$F80>=K$6),"X","") | L80: =IF(AND($E80<=L$6,$F80>=L$6),"X","") | M80: =IF(AND($E80<=M$6,$F80>=M$6),"X","") | N80: =IF(AND($E80<=N$6,$F80>=N$6),"X","") | O80: =IF(AND($E80<=O$6,$F80>=O$6),"X","") | P80: =IF(AND($E80<=P$6,$F80>=P$6),"X","") | ... ES80: =IF(AND($E80<=ES$6,$F80>=ES$6),"X","")

Sheet Expenses
A1: Date | B1: Type | C1: Category | D1: Vendor | E1: Memo | F1: Debit | G1: Credit | H1: Balance
A2: 3/10/1023 | B2: Deposit | E2: Shiraz Contribution | G2: 290000 | H2: =G2-F2 -> 290000
A3: 44995 | B3: CHK | C3: Land Costs | E3: Contract Deposit | F3: 290000 | H3: =(G3-F3)+H2 -> 0
A4: 45044 | B4: Deposit | E4: NYC Cleaning Contribution | G4: 50000 | H4: =(G4-F4)+H3 -> 50000
A5: 45044 | B5: Zelle | C5: Soft Costs | D5: 5 Borough Mapping NY | F5: 750 | H5: =(G5-F5)+H4 -> 49250
A6: 45048 | B6: Wire | C6: Soft Costs | D6: International Office of Architects | E6: Deposit to Architect | F6: 20000 | H6: =(G6-F6)+H5 -> 29250
A7: 45058 | B7: ACH | C7: Soft Costs | D7: Preferred Bank | E7: Deposit for Aquisition Loan | F7: 5000 | H7: =(G7-F7)+H6 -> 24250
A8: 45063 | B8: CHK | C8: Soft Costs | D8: Middleton Environmental | E8: Phase 1 | F8: 1800 | H8: =(G8-F8)+H7 -> 22450
A9: 45064 | B9: ACH | C9: Soft Costs | D9: Stroh Engineering Services | F9: 4500 | H9: =(G9-F9)+H8 -> 17950
A10: 45068 | B10: ACH | C10: Soft Costs | D10: DGM CPA | F10: 613 | H10: =(G10-F10)+H9 -> 17337
A11: 45092 | B11: ACH | C11: Soft Costs | D11: DGM CPA | E11: LLC Creation | F11: 375 | H11: =(G11-F11)+H10 -> 16962
A12: 45092 | B12: ACH | C12: Soft Costs | D12: DGM CPA | E12: LLC Creation | F12: 375 | H12: =(G12-F12)+H11 -> 16587
A13: 45118 | B13: ACH | C13: Soft Costs | D13: Boyd Consulting | E13: Reimbursed Investmates for payment to Expeditor for Demo | F13: 1800 | H13: =(G13-F13)+H12 -> 14787
A14: 45125 | B14: ACH | C14: Soft Costs | D14: Marcus Attorneys PLLC | E14: Review of Operating Agreement | F14: 1080 | H14: =(G14-F14)+H13 -> 13707
A15: 45155 | B15: ACH | C15: Soft Costs | D15: Preferred Bank | E15: Good Faith Deposit | F15: 350 | H15: =(G15-F15)+H14 -> 13357
A16: 45155 | B16: ACH | C16: Soft Costs | D16: Exterior Design Renterings | E16: Payment for Exterior Rendering | F16: 622.99 | H16: =(G16-F16)+H15 -> 12734.01
A17: 45167 | B17: Deposit | E17: NYC Cleaning Contribution | G17: 50000 | H17: =(G17-F17)+H16 -> 62734.01
A18: 45167 | B18: Wire | C18: Soft Costs | D18: International Office of Architects | E18: Second Payment to Architect | F18: 14427 | H18: =(G18-F18)+H17 -> 48307.01
A19: 45228 | B19: ACH | C19: Soft Costs | D19: Yaker Engineering | E19: Deposit for Structural and SSP | F19: 16650 | H19: =(G19-F19)+H18 -> 31657.01
A20: 45299 | B20: Zelle | C20: Soft Costs | D20: WJY MEP Consulting Services, Inc | E20: Deposit for MEP | F20: 4000 | H20: =(G20-F20)+H19 -> 27657.01
A21: 45337 | B21: Deposit | E21: NYC Cleaning Contribution | G21: 10000 | H21: =(G21-F21)+H20 -> 37657.01
A22: 45337 | B22: Wire | C22: Soft Costs | D22: International Office of Architects | E22: 30% Payment for Design Documents | F22: 30000 | H22: =(G22-F22)+H21 -> 7657.01
A23: 45401 | B23: Deposit | E23: Morgan Stanley Interest Income | G23: 2690.17 | H23: =(G23-F23)+H22 -> 10347.18
A24: 45401 | B24: Wire | E24: Interest Payment to Solomon Isakov | F24: 2540.17 | H24: =(G24-F24)+H23 -> 7807.01
A25: 45461 | B25: Deposit | E25: Shiraz Contribution | G25: 25000 | H25: =(G25-F25)+H24 -> 32807.01
A26: 45463 | B26: Wire | C26: Soft Costs | D26: International Office of Architects | E26: Third Payment | F26: 26250 | H26: =(G26-F26)+H25 -> 6557.01

Sheet Contracts
A1: Date | B1: Vendor | C1: Contract Total | D1: Total Paid | E1: Total Remaining
A2: 45047 | B2: Stroh Engineering Services | C2: 9000 | D2: =sumif(Expenses!D$2:D1000,B2,Expenses!F$2:F1000) -> 4500 | E2: =C2-D2 -> 4500
A3: 45044 | B3: International Office of Architects | C3: 100000 | D3: =sumif(Expenses!D$2:D1000,B3,Expenses!F$2:F1000) -> 90677 | E3: =C3-D3 -> 9323
A4: 45228 | B4: Yaker Engineering | C4: 28650 | D4: =sumif(Expenses!D$2:D1000,B4,Expenses!F$2:F1000) -> 16650 | E4: =C4-D4 -> 12000
A5: 45296 | B5: WJY MEP Consulting Services, Inc | C5: 15000 | D5: 4000 | E5: =C5-D5 -> 11000

Sheet Insurances & Permits
A2: Insurances & Contracts
A3: Company | B3: Subcontractor | C3: Contract Signed | D3: Subcontractor Rider | E3: Additional Insured | F3: Workers Comp | G3: General Liability | H3: Workers Comp Expiration | I3: Workers Comp Expiration (d) | J3: General Liability Expiration | K3: General Liability Expiration(d)
A4: Trysler | B4: Mason | C4: YES | D4: YES | E4: YES | F4: YES | G4: State Farm Fire & Casulty | H4: 44866 | I4: =IF(H4="","",ROUNDUP($H4-today(),0)) -> -1283 | J4: 44961 | K4: =IF(J4="","",ROUNDUP(J4-today(),0)) -> -1188
A5: First Choice Pl | B5: Sewer | C5: YES | D5: NO | E5: NO | F5: NO | I5: =IF(H5="","",ROUNDUP($H5-today(),0)) | K5: =IF(J5="","",ROUNDUP(J5-today(),0))
A6: Greenstar Electrical | B6: Electrician | C6: YES | D6: YES | E6: YES | F6: YES | G6: Trisura Specialty Insurance Company | H6: 44779 | I6: =IF(H6="","",ROUNDUP($H6-today(),0)) -> -1370 | J6: 44779 | K6: =IF(J6="","",ROUNDUP(J6-today(),0)) -> -1370
A7: Otis Elevator | B7: Elevator | C7: YES | D7: NO | E7: YES | F7: YES | I7: =IF(H7="","",ROUNDUP($H7-today(),0)) | K7: =IF(J7="","",ROUNDUP(J7-today(),0))
A8: Raymond Plumber | B8: Plumber | C8: YES | D8: NO | I8: =IF(H8="","",ROUNDUP($H8-today(),0)) | K8: =IF(J8="","",ROUNDUP(J8-today(),0))
A9: Capri Construction Corp | B9: Foundation | C9: NO | D9: NO | E9: YES | F9: YES | G9: Accredited Surety and Casualty Company, Inc. | H9: 44927 | I9: =IF(H9="","",ROUNDUP($H9-today(),0)) -> -1222 | J9: 44828 | K9: =IF(J9="","",ROUNDUP(J9-today(),0)) -> -1321
A14: Permits
A15: Address | B15: Permit Type | C15: Agency | D15: Permit Number | E15: Contractor | F15: Contact | G15: Superintendent | H15: Expiration | I15: Number of Days Left
A17: 74-76 Congress Street | B17: Fence | C17: DOB | D17: B00340452-I1-FN | E17: GIRON CONTRACTING INC | F17: 718-690-1370 | H17: 44866 | I17: =IF(H17="","",ROUNDUP($H17-today(),0)) -> -1283
A18: 74-76 Congress Street | B18: Structural | C18: DOB | D18: B00340502-I1-ST | E18: GIRON CONTRACTING INC | F18: 718-690-1370 | H18: 44866 | I18: =IF(H18="","",ROUNDUP($H18-today(),0)) -> -1283
A19: 74-76 Congress Street | B19: Sidewalk Shed & Wiring and Lights | C19: DOB | D19: B00542874-I1-EL | E19: V.VASS ELECTRIC CORP | F19: 347-662-4896 | H19: 44762 | I19: =IF(H19="","",ROUNDUP($H19-today(),0)) -> -1387
A20: 74-76 Congress Street | B20: Temporary Pipe Scaffold Per Plan | C20: DOB | D20: B00542374-I1-SF | E20: CORE SCAFFOLD SYSTEMS INC | F20: 347-662-4896 | H20: 44733 | I20: =IF(H20="","",ROUNDUP($H20-today(),0)) -> -1416
A21: 74-76 Congress Street | B21: Temporary Sidewalk Shed | C21: DOB | D21: B00542355-I1-SH | E21: CORE SCAFFOLD SYSTEMS INC | F21: 347-662-4896 | H21: 44733 | I21: =IF(H21="","",ROUNDUP($H21-today(),0)) -> -1416
A22: 74-76 Congress Street | B22: Temporary Electrical on Job site | C22: DOB | D22: B00705224-I1-EL | E22: GREEN STAR ELECTRICAL | F22: 347-683-9222 | H22: 44779 | I22: =IF(H22="","",ROUNDUP($H22-today(),0)) -> -1370
A23: 74-76 Congress Street | B23: 0132 - INSTALL FENCE | C23: DOT | D23: B01-2022059-A00 | E23: GIRON CONTRACTING INC | F23: 718-690-1370 | H23: 44646 | I23: =IF(H23="","",ROUNDUP($H23-today(),0)) -> -1503
A24: 74-76 Congress Street | B24: 0201 - PLACE MATERIAL ON STREET | C24: DOT | D24: B02-2022059-A00 | E24: GIRON CONTRACTING INC | F24: 718-690-1370 | H24: 44698 | I24: =IF(H24="","",ROUNDUP($H24-today(),0)) -> -1451
A25: 74-76 Congress Street | B25: 0202 - CROSSING SIDEWALK | C25: DOT | D25: B02-2022059-A01 | E25: GIRON CONTRACTING INC | F25: 718-690-1370 | H25: 44698 | I25: =IF(H25="","",ROUNDUP($H25-today(),0)) -> -1451
A26: 74-76 Congress Street | B26: 0215 - OCCUPANCY OF SIDEWALK AS STIPULATED | C26: DOT | D26: B02-2022059-A02 | E26: GIRON CONTRACTING INC | F26: 718-690-1370 | H26: 44722 | I26: =IF(H26="","",ROUNDUP($H26-today(),0)) -> -1427
A27: 74-76 Congress Street | B27: 0221 - TEMP. CONST. SIGNS/MARKINGS | C27: DOT | D27: B02-2022147-D00 | E27: GIRON CONTRACTING INC | F27: 718-690-1370 | H27: 44790 | I27: =IF(H27="","",ROUNDUP($H27-today(),0)) -> -1359
A28: 74-76 Congress Street | B28: 0204 - PLACE EQUIPMENT OTHER THAN CRANE OR | C28: DOT | D28: B02-2022059-A04 | E28: GIRON CONTRACTING INC | F28: 718-690-1370 | H28: 44698 | I28: =IF(H28="","",ROUNDUP($H28-today(),0)) -> -1451

Sheet Lookup
A1: Company | Name | B1: =IFERROR(__xludf.DUMMYFUNCTION("IMPORTRANGE(""https://docs.google.com/spreadsheets/d/1QohlZC4KvRNd994pgsw7OAWCfv3QU1As0i-jXf_d4kQ/edit#gid=0"", ""Contact List!A1:E"")"),"Name") -> Name | C1: =IFERROR(__xludf.DUMMYFUNCTION("""COMPUTED_VALUE"""),"Company Name") -> Company Name | D1: =IFERROR(__xludf.DUMMYFUNCTION("""COMPUTED_VALUE"""),"Office") -> Office | E1: =IFERROR(__xludf.DUMMYFUNCTION("""COMPUTED_VALUE"""),"Mobile") -> Mobile | F1: =IFERROR(__xludf.DUMMYFUNCTION("""COMPUTED_VALUE"""),"Email") -> Email
A2: =if(len(B2>0),CONCATENATE(C2," | ",B2),"") -> Brookside Environmental | Richard Taylor | B2: =IFERROR(__xludf.DUMMYFUNCTION("""COMPUTED_VALUE"""),"Richard Taylor") -> Richard Taylor | C2: =IFERROR(__xludf.DUMMYFUNCTION("""COMPUTED_VALUE"""),"Brookside Environmental") -> Brookside Environmental | D2: =IFERROR(__xludf.DUMMYFUNCTION("""COMPUTED_VALUE"""),"(631) 608-8810") -> (631) 608-8810 | E2: =IFERROR(__xludf.DUMMYFUNCTION("""COMPUTED_VALUE"""),"516-852-1631") -> 516-852-1631 | F2: =IFERROR(__xludf.DUMMYFUNCTION("""COMPUTED_VALUE"""),"rtaylor@brooksideweb.com") -> rtaylor@brooksideweb.com
A3: =if(len(B3>0),CONCATENATE(C3," | ",B3),"") -> Design Studio Associates NY Inc. | Renzo Bolarte | B3: =IFERROR(__xludf.DUMMYFUNCTION("""COMPUTED_VALUE"""),"Renzo Bolarte") -> Renzo Bolarte | C3: =IFERROR(__xludf.DUMMYFUNCTION("""COMPUTED_VALUE"""),"Design Studio Associates NY Inc.") -> Design Studio Associates NY Inc. | D3: =IFERROR(__xludf.DUMMYFUNCTION("""COMPUTED_VALUE"""),"(718) 569-2112") -> (718) 569-2112 | E3: =IFERROR(__xludf.DUMMYFUNCTION("""COMPUTED_VALUE"""),"(516) 642-6960") -> (516) 642-6960 | F3: =IFERROR(__xludf.DUMMYFUNCTION("""COMPUTED_VALUE"""),"renzo@dsany.com") -> renzo@dsany.com
A4: =if(len(B4>0),CONCATENATE(C4," | ",B4),"") -> Engineering Solutions | Jeffrey Spivak | B4: =IFERROR(__xludf.DUMMYFUNCTION("""COMPUTED_VALUE"""),"Jeffrey Spivak") -> Jeffrey Spivak | C4: =IFERROR(__xludf.DUMMYFUNCTION("""COMPUTED_VALUE"""),"Engineering Solutions") -> Engineering Solutions | D4: =IFERROR(__xludf.DUMMYFUNCTION("""COMPUTED_VALUE"""),"212-840-1030 x204") -> 212-840-1030 x204 | F4: =IFERROR(__xludf.DUMMYFUNCTION("""COMPUTED_VALUE"""),"jeff@engsolu.com") -> jeff@engsolu.com
A5: =if(len(B5>0),CONCATENATE(C5," | ",B5),"") -> Greenworks Lending from Nuveen | Crystal Smith | B5: =IFERROR(__xludf.DUMMYFUNCTION("""COMPUTED_VALUE"""),"Crystal Smith") -> Crystal Smith | C5: =IFERROR(__xludf.DUMMYFUNCTION("""COMPUTED_VALUE"""),"Greenworks Lending from Nuveen") -> Greenworks Lending from Nuveen | D5: =IFERROR(__xludf.DUMMYFUNCTION("""COMPUTED_VALUE"""),"(212) 731-2717") -> (212) 731-2717 | F5: =IFERROR(__xludf.DUMMYFUNCTION("""COMPUTED_VALUE"""),"crystal.smith@nuveen.com") -> crystal.smith@nuveen.com
A6: =if(len(B6>0),CONCATENATE(C6," | ",B6),"") -> International Office of Architects | Murat Mutlu | B6: =IFERROR(__xludf.DUMMYFUNCTION("""COMPUTED_VALUE"""),"Murat Mutlu") -> Murat Mutlu | C6: =IFERROR(__xludf.DUMMYFUNCTION("""COMPUTED_VALUE"""),"International Office of Architects") -> International Office of Architects | D6: =IFERROR(__xludf.DUMMYFUNCTION("""COMPUTED_VALUE"""),"(212) 564-0094") -> (212) 564-0094 | E6: =IFERROR(__xludf.DUMMYFUNCTION("""COMPUTED_VALUE"""),"(607) 262-0368") -> (607) 262-0368 | F6: =IFERROR(__xludf.DUMMYFUNCTION("""COMPUTED_VALUE"""),"murat@in-oa.com") -> murat@in-oa.com
A7: =if(len(B7>0),CONCATENATE(C7," | ",B7),"") -> IRL Systems | Brendan Lally | B7: =IFERROR(__xludf.DUMMYFUNCTION("""COMPUTED_VALUE"""),"Brendan Lally ") -> Brendan Lally | C7: =IFERROR(__xludf.DUMMYFUNCTION("""COMPUTED_VALUE"""),"IRL Systems") -> IRL Systems | F7: =IFERROR(__xludf.DUMMYFUNCTION("""COMPUTED_VALUE"""),"brendanl@irlsystems.com") -> brendanl@irlsystems.com
A8: =if(len(B8>0),CONCATENATE(C8," | ",B8),"") -> Middleton Environmental | Thomas R. Tompkins | B8: =IFERROR(__xludf.DUMMYFUNCTION("""COMPUTED_VALUE"""),"Thomas R. Tompkins") -> Thomas R. Tompkins | C8: =IFERROR(__xludf.DUMMYFUNCTION("""COMPUTED_VALUE"""),"Middleton Environmental") -> Middleton Environmental | D8: =IFERROR(__xludf.DUMMYFUNCTION("""COMPUTED_VALUE"""),"(631) 321-4300") -> (631) 321-4300 | F8: =IFERROR(__xludf.DUMMYFUNCTION("""COMPUTED_VALUE"""),"info@midenv.com") -> info@midenv.com
A9: =if(len(B9>0),CONCATENATE(C9," | ",B9),"") -> One Concrete | Izzy Lubart | B9: =IFERROR(__xludf.DUMMYFUNCTION("""COMPUTED_VALUE"""),"Izzy Lubart") -> Izzy Lubart | C9: =IFERROR(__xludf.DUMMYFUNCTION("""COMPUTED_VALUE"""),"One Concrete") -> One Concrete | F9: =IFERROR(__xludf.DUMMYFUNCTION("""COMPUTED_VALUE"""),"Izzy@Oneconcrete.net") -> Izzy@Oneconcrete.net
A10: =if(len(B10>0),CONCATENATE(C10," | ",B10),"") -> Peerless Products | Jamie McKnight | B10: =IFERROR(__xludf.DUMMYFUNCTION("""COMPUTED_VALUE"""),"Jamie McKnight ") -> Jamie McKnight | C10: =IFERROR(__xludf.DUMMYFUNCTION("""COMPUTED_VALUE"""),"Peerless Products") -> Peerless Products | D10: =IFERROR(__xludf.DUMMYFUNCTION("""COMPUTED_VALUE"""),"401-487-6686") -> 401-487-6686 | F10: =IFERROR(__xludf.DUMMYFUNCTION("""COMPUTED_VALUE"""),"repmcknight33@gmail.com") -> repmcknight33@gmail.com
A11: =if(len(B11>0),CONCATENATE(C11," | ",B11),"") -> Pella Windows | Leo Zonenshein | B11: =IFERROR(__xludf.DUMMYFUNCTION("""COMPUTED_VALUE"""),"Leo Zonenshein") -> Leo Zonenshein | C11: =IFERROR(__xludf.DUMMYFUNCTION("""COMPUTED_VALUE"""),"Pella Windows") -> Pella Windows | D11: =IFERROR(__xludf.DUMMYFUNCTION("""COMPUTED_VALUE"""),"646-773-6405") -> 646-773-6405 | F11: =IFERROR(__xludf.DUMMYFUNCTION("""COMPUTED_VALUE"""),"LZonenshein@pellactny.com") -> LZonenshein@pellactny.com
A12: =if(len(B12>0),CONCATENATE(C12," | ",B12),"") -> Renovation Group | Daniel Kaykov | B12: =IFERROR(__xludf.DUMMYFUNCTION("""COMPUTED_VALUE"""),"Daniel Kaykov") -> Daniel Kaykov | C12: =IFERROR(__xludf.DUMMYFUNCTION("""COMPUTED_VALUE"""),"Renovation Group") -> Renovation Group | E12: =IFERROR(__xludf.DUMMYFUNCTION("""COMPUTED_VALUE"""),"(718) 690-1370") -> (718) 690-1370 | F12: =IFERROR(__xludf.DUMMYFUNCTION("""COMPUTED_VALUE"""),"dan@renovationgroup.com") -> dan@renovationgroup.com
A13: =if(len(B13>0),CONCATENATE(C13," | ",B13),"") -> Rosen Law | Jaime Rosen Esq | B13: =IFERROR(__xludf.DUMMYFUNCTION("""COMPUTED_VALUE"""),"Jaime Rosen Esq") -> Jaime Rosen Esq | C13: =IFERROR(__xludf.DUMMYFUNCTION("""COMPUTED_VALUE"""),"Rosen Law") -> Rosen Law | F13: =IFERROR(__xludf.DUMMYFUNCTION("""COMPUTED_VALUE"""),"jaime@rosenlawllc.com") -> jaime@rosenlawllc.com
A14: =if(len(B14>0),CONCATENATE(C14," | ",B14),"") -> Soil Safe | James Case | B14: =IFERROR(__xludf.DUMMYFUNCTION("""COMPUTED_VALUE"""),"James Case") -> James Case | C14: =IFERROR(__xludf.DUMMYFUNCTION("""COMPUTED_VALUE"""),"Soil Safe") -> Soil Safe | D14: =IFERROR(__xludf.DUMMYFUNCTION("""COMPUTED_VALUE"""),"(516) 605-2110 x30346") -> (516) 605-2110 x30346 | E14: =IFERROR(__xludf.DUMMYFUNCTION("""COMPUTED_VALUE"""),"(516) 972-3896") -> (516) 972-3896 | F14: =IFERROR(__xludf.DUMMYFUNCTION("""COMPUTED_VALUE"""),"james.case@gflenv.com") -> james.case@gflenv.com
A15: =if(len(B15>0),CONCATENATE(C15," | ",B15),"") -> StudioGallos Architecture | Frankie Nunez | B15: =IFERROR(__xludf.DUMMYFUNCTION("""COMPUTED_VALUE"""),"Frankie Nunez") -> Frankie Nunez | C15: =IFERROR(__xludf.DUMMYFUNCTION("""COMPUTED_VALUE"""),"StudioGallos Architecture") -> StudioGallos Architecture | D15: =IFERROR(__xludf.DUMMYFUNCTION("""COMPUTED_VALUE"""),"(718) 458-1518 x2102") -> (718) 458-1518 x2102 | F15: =IFERROR(__xludf.DUMMYFUNCTION("""COMPUTED_VALUE"""),"fnunez@studiogallos.com") -> fnunez@studiogallos.com
A16: =if(len(B16>0),CONCATENATE(C16," | ",B16),"") -> | Mohammad Aftab | B16: =IFERROR(__xludf.DUMMYFUNCTION("""COMPUTED_VALUE"""),"Mohammad Aftab") -> Mohammad Aftab | D16: =IFERROR(__xludf.DUMMYFUNCTION("""COMPUTED_VALUE"""),"(917) 560-6994") -> (917) 560-6994 | F16: =IFERROR(__xludf.DUMMYFUNCTION("""COMPUTED_VALUE"""),"aftabshahnoc@gmail.com") -> aftabshahnoc@gmail.com
A17: =if(len(B17>0),CONCATENATE(C17," | ",B17),"") -> Perciballi Industries Inc | Mike Perciballi | B17: =IFERROR(__xludf.DUMMYFUNCTION("""COMPUTED_VALUE"""),"Mike Perciballi") -> Mike Perciballi | C17: =IFERROR(__xludf.DUMMYFUNCTION("""COMPUTED_VALUE"""),"Perciballi Industries Inc") -> Perciballi Industries Inc | D17: =IFERROR(__xludf.DUMMYFUNCTION("""COMPUTED_VALUE"""),"(347) 825-3781") -> (347) 825-3781 | E17: =IFERROR(__xludf.DUMMYFUNCTION("""COMPUTED_VALUE"""),"(646) 248-2012 ") -> (646) 248-2012 | F17: =IFERROR(__xludf.DUMMYFUNCTION("""COMPUTED_VALUE"""),"mikep@perciballiindustriesinc.com") -> mikep@perciballiindustriesinc.com
A18: =if(len(B18>0),CONCATENATE(C18," | ",B18),"") -> Celtic Demolition | Mike | B18: =IFERROR(__xludf.DUMMYFUNCTION("""COMPUTED_VALUE"""),"Mike") -> Mike | C18: =IFERROR(__xludf.DUMMYFUNCTION("""COMPUTED_VALUE"""),"Celtic Demolition") -> Celtic Demolition | E18: =IFERROR(__xludf.DUMMYFUNCTION("""COMPUTED_VALUE"""),"914-704-5511") -> 914-704-5511 | F18: =IFERROR(__xludf.DUMMYFUNCTION("""COMPUTED_VALUE"""),"mike@cltgrp.com") -> mike@cltgrp.com
A19: =if(len(B19>0),CONCATENATE(C19," | ",B19),"") -> North East Specialist Group | Nick Sopasoudakis | B19: =IFERROR(__xludf.DUMMYFUNCTION("""COMPUTED_VALUE"""),"Nick Sopasoudakis") -> Nick Sopasoudakis | C19: =IFERROR(__xludf.DUMMYFUNCTION("""COMPUTED_VALUE"""),"North East Specialist Group") -> North East Specialist Group | E19: =IFERROR(__xludf.DUMMYFUNCTION("""COMPUTED_VALUE"""),"347-756-2641") -> 347-756-2641 | F19: =IFERROR(__xludf.DUMMYFUNCTION("""COMPUTED_VALUE"""),"nsopas@northeastsg.com") -> nsopas@northeastsg.com
A20: =if(len(B20>0),CONCATENATE(C20," | ",B20),"") -> Stroh Engineering Services | Jeff Roberts | B20: =IFERROR(__xludf.DUMMYFUNCTION("""COMPUTED_VALUE"""),"Jeff Roberts") -> Jeff Roberts | C20: =IFERROR(__xludf.DUMMYFUNCTION("""COMPUTED_VALUE"""),"Stroh Engineering Services ") -> Stroh Engineering Services | D20: =IFERROR(__xludf.DUMMYFUNCTION("""COMPUTED_VALUE"""),"631-669-7531") -> 631-669-7531 | E20: =IFERROR(__xludf.DUMMYFUNCTION("""COMPUTED_VALUE"""),"516-351-2150") -> 516-351-2150 | F20: =IFERROR(__xludf.DUMMYFUNCTION("""COMPUTED_VALUE"""),"jeff@strohengineering.com") -> jeff@strohengineering.com
A21: =if(len(B21>0),CONCATENATE(C21," | ",B21),"") -> Boyd Consulting | Andrea Boyd | B21: =IFERROR(__xludf.DUMMYFUNCTION("""COMPUTED_VALUE"""),"Andrea Boyd") -> Andrea Boyd | C21: =IFERROR(__xludf.DUMMYFUNCTION("""COMPUTED_VALUE"""),"Boyd Consulting") -> Boyd Consulting | D21: =IFERROR(__xludf.DUMMYFUNCTION("""COMPUTED_VALUE"""),"646-619-3620 ") -> 646-619-3620 | F21: =IFERROR(__xludf.DUMMYFUNCTION("""COMPUTED_VALUE"""),"andrea@boydconsult.com") -> andrea@boydconsult.com
A22: =if(len(B22>0),CONCATENATE(C22," | ",B22),"") -> 5 Borough Mapping NY | Raj Kumar | B22: =IFERROR(__xludf.DUMMYFUNCTION("""COMPUTED_VALUE"""),"Raj Kumar") -> Raj Kumar | C22: =IFERROR(__xludf.DUMMYFUNCTION("""COMPUTED_VALUE"""),"5 Borough Mapping NY") -> 5 Borough Mapping NY | D22: =IFERROR(__xludf.DUMMYFUNCTION("""COMPUTED_VALUE"""),"516-652-9984") -> 516-652-9984 | F22: =IFERROR(__xludf.DUMMYFUNCTION("""COMPUTED_VALUE"""),"5boromapping@gmail.com") -> 5boromapping@gmail.com
A23: =if(len(B23>0),CONCATENATE(C23," | ",B23),"") -> Preferred Bank | Sylvia Tseng | B23: =IFERROR(__xludf.DUMMYFUNCTION("""COMPUTED_VALUE"""),"Sylvia Tseng") -> Sylvia Tseng | C23: =IFERROR(__xludf.DUMMYFUNCTION("""COMPUTED_VALUE"""),"Preferred Bank") -> Preferred Bank | D23: =IFERROR(__xludf.DUMMYFUNCTION("""COMPUTED_VALUE"""),"(347) 532-8038") -> (347) 532-8038 | F23: =IFERROR(__xludf.DUMMYFUNCTION("""COMPUTED_VALUE"""),"Sylvia.Tseng@PreferredBank.com") -> Sylvia.Tseng@PreferredBank.com
A24: =if(len(B24>0),CONCATENATE(C24," | ",B24),"") -> DGM CPA | George Mataev | B24: =IFERROR(__xludf.DUMMYFUNCTION("""COMPUTED_VALUE"""),"George Mataev") -> George Mataev | C24: =IFERROR(__xludf.DUMMYFUNCTION("""COMPUTED_VALUE"""),"DGM CPA") -> DGM CPA | D24: =IFERROR(__xludf.DUMMYFUNCTION("""COMPUTED_VALUE"""),"718-530-4545") -> 718-530-4545 | F24: =IFERROR(__xludf.DUMMYFUNCTION("""COMPUTED_VALUE"""),"george@dgmcpany.com") -> george@dgmcpany.com
A25: =if(len(B25>0),CONCATENATE(C25," | ",B25),"") -> Marcus Attorneys PLLC | Guillermo Santiago | B25: =IFERROR(__xludf.DUMMYFUNCTION("""COMPUTED_VALUE"""),"Guillermo Santiago") -> Guillermo Santiago | C25: =IFERROR(__xludf.DUMMYFUNCTION("""COMPUTED_VALUE"""),"Marcus Attorneys PLLC") -> Marcus Attorneys PLLC | D25: =IFERROR(__xludf.DUMMYFUNCTION("""COMPUTED_VALUE"""),"718-233-2564") -> 718-233-2564 | F25: =IFERROR(__xludf.DUMMYFUNCTION("""COMPUTED_VALUE"""),"santiago@marcusattorneys.com") -> santiago@marcusattorneys.com
A26: =if(len(B26>0),CONCATENATE(C26," | ",B26),"") -> MCAI Construction Services | Noel G Muir | B26: =IFERROR(__xludf.DUMMYFUNCTION("""COMPUTED_VALUE"""),"Noel G Muir") -> Noel G Muir | C26: =IFERROR(__xludf.DUMMYFUNCTION("""COMPUTED_VALUE"""),"MCAI Construction Services") -> MCAI Construction Services | D26: =IFERROR(__xludf.DUMMYFUNCTION("""COMPUTED_VALUE"""),"516-288-8546") -> 516-288-8546 | F26: =IFERROR(__xludf.DUMMYFUNCTION("""COMPUTED_VALUE"""),"mcai079@aol.com") -> mcai079@aol.com
A27: =if(len(B27>0),CONCATENATE(C27," | ",B27),"") -> Exterior Design Renterings | Andrew Melnikov | B27: =IFERROR(__xludf.DUMMYFUNCTION("""COMPUTED_VALUE"""),"Andrew Melnikov") -> Andrew Melnikov | C27: =IFERROR(__xludf.DUMMYFUNCTION("""COMPUTED_VALUE"""),"Exterior Design Renterings") -> Exterior Design Renterings | D27: =IFERROR(__xludf.DUMMYFUNCTION("""COMPUTED_VALUE"""),"380 66 198 7396") -> 380 66 198 7396
A28: =if(len(B28>0),CONCATENATE(C28," | ",B28),"") -> Yaker Engineering | Alex Yaker | B28: =IFERROR(__xludf.DUMMYFUNCTION("""COMPUTED_VALUE"""),"Alex Yaker") -> Alex Yaker | C28: =IFERROR(__xludf.DUMMYFUNCTION("""COMPUTED_VALUE"""),"Yaker Engineering") -> Yaker Engineering | D28: =IFERROR(__xludf.DUMMYFUNCTION("""COMPUTED_VALUE"""),"917-518-2032") -> 917-518-2032 | F28: =IFERROR(__xludf.DUMMYFUNCTION("""COMPUTED_VALUE"""),"ayaker@yakereng.com") -> ayaker@yakereng.com
A29: =if(len(B29>0),CONCATENATE(C29," | ",B29),"") -> ADG Engineering | Aamer Islam | B29: =IFERROR(__xludf.DUMMYFUNCTION("""COMPUTED_VALUE"""),"Aamer Islam") -> Aamer Islam | C29: =IFERROR(__xludf.DUMMYFUNCTION("""COMPUTED_VALUE"""),"ADG Engineering") -> ADG Engineering | D29: =IFERROR(__xludf.DUMMYFUNCTION("""COMPUTED_VALUE"""),"212-288-7120") -> 212-288-7120 | E29: =IFERROR(__xludf.DUMMYFUNCTION("""COMPUTED_VALUE"""),"917-509-4148") -> 917-509-4148 | F29: =IFERROR(__xludf.DUMMYFUNCTION("""COMPUTED_VALUE"""),"aislam@axisd.com") -> aislam@axisd.com
A30: =if(len(B30>0),CONCATENATE(C30," | ",B30),"") -> Active Environmental Corp. | Romeo Santos | B30: =IFERROR(__xludf.DUMMYFUNCTION("""COMPUTED_VALUE"""),"Romeo Santos") -> Romeo Santos | C30: =IFERROR(__xludf.DUMMYFUNCTION("""COMPUTED_VALUE"""),"Active Environmental Corp.") -> Active Environmental Corp. | D30: =IFERROR(__xludf.DUMMYFUNCTION("""COMPUTED_VALUE"""),"718-854-1111") -> 718-854-1111 | F30: =IFERROR(__xludf.DUMMYFUNCTION("""COMPUTED_VALUE"""),"doncarllo@aol.com") -> doncarllo@aol.com
A31: =if(len(B31>0),CONCATENATE(C31," | ",B31),"") -> WJY MEP Consulting Services, Inc | Wei Wang | B31: =IFERROR(__xludf.DUMMYFUNCTION("""COMPUTED_VALUE"""),"Wei Wang") -> Wei Wang | C31: =IFERROR(__xludf.DUMMYFUNCTION("""COMPUTED_VALUE"""),"WJY MEP Consulting Services, Inc") -> WJY MEP Consulting Services, Inc | D31: =IFERROR(__xludf.DUMMYFUNCTION("""COMPUTED_VALUE"""),"917-815-5366") -> 917-815-5366 | F31: =IFERROR(__xludf.DUMMYFUNCTION("""COMPUTED_VALUE"""),"weiwilliamworld@yahoo.com") -> weiwilliamworld@yahoo.com
A32: =if(len(B32>0),CONCATENATE(C32," | ",B32),"") -> Safari Energy Engineering | Yoichi Chiba | B32: =IFERROR(__xludf.DUMMYFUNCTION("""COMPUTED_VALUE"""),"Yoichi Chiba") -> Yoichi Chiba | C32: =IFERROR(__xludf.DUMMYFUNCTION("""COMPUTED_VALUE"""),"Safari Energy Engineering") -> Safari Energy Engineering | D32: =IFERROR(__xludf.DUMMYFUNCTION("""COMPUTED_VALUE"""),"347-506-0277") -> 347-506-0277 | E32: =IFERROR(__xludf.DUMMYFUNCTION("""COMPUTED_VALUE"""),"929-204-9438") -> 929-204-9438 | F32: =IFERROR(__xludf.DUMMYFUNCTION("""COMPUTED_VALUE"""),"jack@safariny.com") -> jack@safariny.com
A33: =if(len(B33>0),CONCATENATE(C33," | ",B33),"") -> Regional Testing Corp | Pamela Fajek | B33: =IFERROR(__xludf.DUMMYFUNCTION("""COMPUTED_VALUE"""),"Pamela Fajek") -> Pamela Fajek | C33: =IFERROR(__xludf.DUMMYFUNCTION("""COMPUTED_VALUE"""),"Regional Testing Corp") -> Regional Testing Corp | D33: =IFERROR(__xludf.DUMMYFUNCTION("""COMPUTED_VALUE"""),"347-221-0110") -> 347-221-0110 | F33: =IFERROR(__xludf.DUMMYFUNCTION("""COMPUTED_VALUE"""),"pfajek@regionaltestingcorp.com") -> pfajek@regionaltestingcorp.com
A34: =if(len(B34>0),CONCATENATE(C34," | ",B34),"") -> |
A35: =if(len(B35>0),CONCATENATE(C35," | ",B35),"") -> |
A36: =if(len(B36>0),CONCATENATE(C36," | ",B36),"") -> |
A37: =if(len(B37>0),CONCATENATE(C37," | ",B37),"") -> |
A38: =if(len(B38>0),CONCATENATE(C38," | ",B38),"") -> |
